Workbook

Sheet AP_Subledger
A1: Invoice_ID | B1: Vendor | C1: Invoice_Date | D1: Due_Date | E1: Project_ID | F1: GL_Account | G1: Amount_Before_Tax | H1: Tax_Jurisdiction | I1: Tax_Amount | J1: Total_Invoice_Amount | K1: Paid_Flag | L1: Paid_Date | M1: Expected_Total | N1: Total_Mismatch_Flag | O1: Unpaid_AsOfYE | P1: AP_Match_Key | Q1: Bank_Match_Status
A2: INV2025-0001 | B2: Tri-County Services | C2: 45760 | D2: 45790 | E2: PRJ-1001 | F2: 5200-Subcontractors | G2: 4994.15 | H2: Pinellas | I2: 349.59 | J2: =IF(RAND()<0.23, M2 + RANDBETWEEN(-150,150)/100, M2) -> 5343.74 | K2: TRUE | L2: 45785 | M2: 5343.74 | N2: =IF(ABS(VALUE(M2) - VALUE(J2)) > 0.01, TRUE, FALSE) -> FALSE | O2: =IF(OR(K2=FALSE, IFERROR(L2>DATE(2025,12,31), TRUE)), TRUE, FALSE) -> FALSE | P2: =B2 & "|" & (-1 * J2) -> Tri-County Services|-5343.74 | Q2: =IF(K2=FALSE, "Unpaid", IF(ISNUMBER(MATCH(P2, Bank_Transactions!H:H, 0)), "Matched in Bank", "Paid but No Bank Match")) -> Paid but No Bank Match
A3: INV2025-0002 | B3: Atlantic Fiber Co | C3: 45760 | D3: 45790 | E3: PRJ-1001 | F3: 2100-AP-Trade | G3: 2949.39 | H3: Other_FL | I3: 176.96 | J3: =IF(RAND()<0.23, M3 + RANDBETWEEN(-150,150)/100, M3) -> 3126.35 | K3: TRUE | L3: 45788 | M3: 3126.35 | N3: =IF(ABS(VALUE(M3) - VALUE(J3)) > 0.01, TRUE, FALSE) -> FALSE | O3: =IF(OR(K3=FALSE, IFERROR(L3>DATE(2025,12,31), TRUE)), TRUE, FALSE) -> FALSE | P3: =B3 & "|" & (-1 * J3) -> Atlantic Fiber Co|-3126.35 | Q3: =IF(K3=FALSE, "Unpaid", IF(ISNUMBER(MATCH(P3, Bank_Transactions!H:H, 0)), "Matched in Bank", "Paid but No Bank Match")) -> Paid but No Bank Match
A4: INV2025-0003 | B4: Sunline Electrical | C4: 45788 | D4: 45818 | E4: PRJ-1001 | F4: 5100-Materials | G4: 24262.79 | H4: Pinellas | I4: 1698.4 | J4: =IF(RAND()<0.23, M4 + RANDBETWEEN(-150,150)/100, M4) -> 25961.19 | K4: TRUE | L4: 45830 | M4: 25961.19 | N4: =IF(ABS(VALUE(M4) - VALUE(J4)) > 0.01, TRUE, FALSE) -> FALSE | O4: =IF(OR(K4=FALSE, IFERROR(L4>DATE(2025,12,31), TRUE)), TRUE, FALSE) -> FALSE | P4: =B4 & "|" & (-1 * J4) -> Sunline Electrical|-25961.19 | Q4: =IF(K4=FALSE, "Unpaid", IF(ISNUMBER(MATCH(P4, Bank_Transactions!H:H, 0)), "Matched in Bank", "Paid but No Bank Match")) -> Paid but No Bank Match
A5: INV2025-0004 | B5: Tidal Contractors | C5: 45849 | D5: 45879 | E5: PRJ-4003 | F5: 9999-Suspense | G5: 15628.3 | H5: Other_FL | I5: 937.7 | J5: =IF(RAND()<0.23, M5 + RANDBETWEEN(-150,150)/100, M5) -> 16566 | K5: TRUE | L5: 45902 | M5: 16566 | N5: =IF(ABS(VALUE(M5) - VALUE(J5)) > 0.01, TRUE, FALSE) -> FALSE | O5: =IF(OR(K5=FALSE, IFERROR(L5>DATE(2025,12,31), TRUE)), TRUE, FALSE) -> FALSE | P5: =B5 & "|" & (-1 * J5) -> Tidal Contractors|-16566 | Q5: =IF(K5=FALSE, "Unpaid", IF(ISNUMBER(MATCH(P5, Bank_Transactions!H:H, 0)), "Matched in Bank", "Paid but No Bank Match")) -> Paid but No Bank Match
A6: INV2025-0005 | B6: Atlantic Fiber Co | C6: 45716 | D6: 45761 | E6: PRJ-4003 | F6: 5200-Subcontractors | G6: 1643.31 | H6: Hillsborough | I6: 123.25 | J6: =IF(RAND()<0.23, M6 + RANDBETWEEN(-150,150)/100, M6) -> 1767.02 | K6: FALSE | M6: 1766.56 | N6: =IF(ABS(VALUE(M6) - VALUE(J6)) > 0.01, TRUE, FALSE) -> TRUE | O6: =IF(OR(K6=FALSE, IFERROR(L6>DATE(2025,12,31), TRUE)), TRUE, FALSE) -> TRUE | P6: =B6 & "|" & (-1 * J6) -> Atlantic Fiber Co|-1767.02 | Q6: =IF(K6=FALSE, "Unpaid", IF(ISNUMBER(MATCH(P6, Bank_Transactions!H:H, 0)), "Matched in Bank", "Paid but No Bank Match")) -> Unpaid
A7: INV2025-0006 | B7: Tampa Grid Services | C7: 45928 | D7: 45973 | E7: PRJ-2001 | F7: 5200-Subcontractors | G7: 19736.81 | H7: Pinellas | I7: 1381.58 | J7: =IF(RAND()<0.23, M7 + RANDBETWEEN(-150,150)/100, M7) -> 21118.39 | K7: TRUE | L7: 45987 | M7: 21118.39 | N7: =IF(ABS(VALUE(M7) - VALUE(J7)) > 0.01, TRUE, FALSE) -> FALSE | O7: =IF(OR(K7=FALSE, IFERROR(L7>DATE(2025,12,31), TRUE)), TRUE, FALSE) -> FALSE | P7: =B7 & "|" & (-1 * J7) -> Tampa Grid Services|-21118.39 | Q7: =IF(K7=FALSE, "Unpaid", IF(ISNUMBER(MATCH(P7, Bank_Transactions!H:H, 0)), "Matched in Bank", "Paid but No Bank Match")) -> Paid but No Bank Match
A8: INV2025-0007 | B8: Atlantic Fiber Co | C8: 45901 | D8: 45946 | E8: PRJ-1001 | F8: 2100-AP-Trade | G8: 1638.04 | H8: Other_FL | I8: 98.28 | J8: =IF(RAND()<0.23, M8 + RANDBETWEEN(-150,150)/100, M8) -> 1736.32 | K8: TRUE | L8: 45926 | M8: 1736.32 | N8: =IF(ABS(VALUE(M8) - VALUE(J8)) > 0.01, TRUE, FALSE) -> FALSE | O8: =IF(OR(K8=FALSE, IFERROR(L8>DATE(2025,12,31), TRUE)), TRUE, FALSE) -> FALSE | P8: =B8 & "|" & (-1 * J8) -> Atlantic Fiber Co|-1736.32 | Q8: =IF(K8=FALSE, "Unpaid", IF(ISNUMBER(MATCH(P8, Bank_Transactions!H:H, 0)), "Matched in Bank", "Paid but No Bank Match")) -> Paid but No Bank Match
A9: INV2025-0008 | B9: Gulf Coast Telecom | C9: 45986 | D9: 46031 | E9: PRJ-2001 | F9: 5200-Subcontractors | G9: 23747.7 | H9: Hillsborough | I9: 1781.08 | J9: =IF(RAND()<0.23, M9 + RANDBETWEEN(-150,150)/100, M9) -> 25528.78 | K9: FALSE | M9: 25528.78 | N9: =IF(ABS(VALUE(M9) - VALUE(J9)) > 0.01, TRUE, FALSE) -> FALSE | O9: =IF(OR(K9=FALSE, IFERROR(L9>DATE(2025,12,31), TRUE)), TRUE, FALSE) -> TRUE | P9: =B9 & "|" & (-1 * J9) -> Gulf Coast Telecom|-25528.78 | Q9: =IF(K9=FALSE, "Unpaid", IF(ISNUMBER(MATCH(P9, Bank_Transactions!H:H, 0)), "Matched in Bank", "Paid but No Bank Match")) -> Unpaid
A10: INV2025-0009 | B10: BrightPower Partners | C10: 45899 | D10: 45944 | E10: PRJ-4003 | F10: 2100-AP-Trade | G10: 891.17 | H10: Other_FL | I10: 53.47 | J10: =IF(RAND()<0.23, M10 + RANDBETWEEN(-150,150)/100, M10) -> 944.64 | K10: TRUE | L10: 45963 | M10: 944.64 | N10: =IF(ABS(VALUE(M10) - VALUE(J10)) > 0.01, TRUE, FALSE) -> FALSE | O10: =IF(OR(K10=FALSE, IFERROR(L10>DATE(2025,12,31), TRUE)), TRUE, FALSE) -> FALSE | P10: =B10 & "|" & (-1 * J10) -> BrightPower Partners|-944.64 | Q10: =IF(K10=FALSE, "Unpaid", IF(ISNUMBER(MATCH(P10, Bank_Transactions!H:H, 0)), "Matched in Bank", "Paid but No Bank Match")) -> Paid but No Bank Match
A11: INV2025-0010 | B11: Gulf Coast Telecom | C11: 45921 | D11: 45966 | E11: PRJ-4003 | F11: 5200-Subcontractors | G11: 22778.35 | H11: Pinellas | I11: 1594.48 | J11: =IF(RAND()<0.23, M11 + RANDBETWEEN(-150,150)/100, M11) -> 24372.83 | K11: TRUE | L11: 45929 | M11: 24372.83 | N11: =IF(ABS(VALUE(M11) - VALUE(J11)) > 0.01, TRUE, FALSE) -> FALSE | O11: =IF(OR(K11=FALSE, IFERROR(L11>DATE(2025,12,31), TRUE)), TRUE, FALSE) -> FALSE | P11: =B11 & "|" & (-1 * J11) -> Gulf Coast Telecom|-24372.83 | Q11: =IF(K11=FALSE, "Unpaid", IF(ISNUMBER(MATCH(P11, Bank_Transactions!H:H, 0)), "Matched in Bank", "Paid but No Bank Match")) -> Paid but No Bank Match
A12: INV2025-0011 | B12: BrightPower Partners | C12: 45659 | D12: 45689 | E12: PRJ-1001 | F12: 5100-Materials | G12: 5594.57 | H12: Orange | I12: 363.65 | J12: =IF(RAND()<0.23, M12 + RANDBETWEEN(-150,150)/100, M12) -> 5958.91 | K12: TRUE | L12: 45726 | M12: 5958.22 | N12: =IF(ABS(VALUE(M12) - VALUE(J12)) > 0.01, TRUE, FALSE) -> TRUE | O12: =IF(OR(K12=FALSE, IFERROR(L12>DATE(2025,12,31), TRUE)), TRUE, FALSE) -> FALSE | P12: =B12 & "|" & (-1 * J12) -> BrightPower Partners|-5958.91 | Q12: =IF(K12=FALSE, "Unpaid", IF(ISNUMBER(MATCH(P12, Bank_Transactions!H:H, 0)), "Matched in Bank", "Paid but No Bank Match")) -> Paid but No Bank Match
A13: INV2025-0012 | B13: Gulf Coast Telecom | C13: 45875 | D13: 45905 | E13: PRJ-1001 | F13: 5300-Equipment-Rental | G13: 10181.18 | H13: Orange | I13: 661.78 | J13: =IF(RAND()<0.23, M13 + RANDBETWEEN(-150,150)/100, M13) -> 10842.96 | K13: FALSE | M13: 10842.96 | N13: =IF(ABS(VALUE(M13) - VALUE(J13)) > 0.01, TRUE, FALSE) -> FALSE | O13: =IF(OR(K13=FALSE, IFERROR(L13>DATE(2025,12,31), TRUE)), TRUE, FALSE) -> TRUE | P13: =B13 & "|" & (-1 * J13) -> Gulf Coast Telecom|-10842.96 | Q13: =IF(K13=FALSE, "Unpaid", IF(ISNUMBER(MATCH(P13, Bank_Transactions!H:H, 0)), "Matched in Bank", "Paid but No Bank Match")) -> Unpaid
A14: INV2025-0013 | B14: Sunshine Equipment | C14: 46008 | D14: 46053 | E14: PRJ-1002 | F14: 6000-Misc-Expense | G14: 2668.07 | H14: Orange | I14: 173.42 | J14: =IF(RAND()<0.23, M14 + RANDBETWEEN(-150,150)/100, M14) -> 2841.49 | K14: FALSE | M14: 2841.49 | N14: =IF(ABS(VALUE(M14) - VALUE(J14)) > 0.01, TRUE, FALSE) -> FALSE | O14: =IF(OR(K14=FALSE, IFERROR(L14>DATE(2025,12,31), TRUE)), TRUE, FALSE) -> TRUE | P14: =B14 & "|" & (-1 * J14) -> Sunshine Equipment|-2841.49 | Q14: =IF(K14=FALSE, "Unpaid", IF(ISNUMBER(MATCH(P14, Bank_Transactions!H:H, 0)), "Matched in Bank", "Paid but No Bank Match")) -> Unpaid
A15: INV2025-0014 | B15: Atlantic Fiber Co | C15: 45953 | D15: 45998 | E15: PRJ-1001 | F15: 5100-Materials | G15: 18809.34 | H15: Pinellas | I15: 1316.65 | J15: =IF(RAND()<0.23, M15 + RANDBETWEEN(-150,150)/100, M15) -> 20125.99 | K15: TRUE | L15: 45981 | M15: 20125.99 | N15: =IF(ABS(VALUE(M15) - VALUE(J15)) > 0.01, TRUE, FALSE) -> FALSE | O15: =IF(OR(K15=FALSE, IFERROR(L15>DATE(2025,12,31), TRUE)), TRUE, FALSE) -> FALSE | P15: =B15 & "|" & (-1 * J15) -> Atlantic Fiber Co|-20125.99 | Q15: =IF(K15=FALSE, "Unpaid", IF(ISNUMBER(MATCH(P15, Bank_Transactions!H:H, 0)), "Matched in Bank", "Paid but No Bank Match")) -> Paid but No Bank Match
A16: INV2025-0015 | B16: Tampa Grid Services | C16: 45874 | D16: 45919 | E16: PRJ-3005 | F16: 5200-Subcontractors | G16: 13796.05 | H16: Pinellas | I16: 965.72 | J16: =IF(RAND()<0.23, M16 + RANDBETWEEN(-150,150)/100, M16) -> 14761.77 | K16: TRUE | L16: 45893 | M16: 14761.77 | N16: =IF(ABS(VALUE(M16) - VALUE(J16)) > 0.01, TRUE, FALSE) -> FALSE | O16: =IF(OR(K16=FALSE, IFERROR(L16>DATE(2025,12,31), TRUE)), TRUE, FALSE) -> FALSE | P16: =B16 & "|" & (-1 * J16) -> Tampa Grid Services|-14761.77 | Q16: =IF(K16=FALSE, "Unpaid", IF(ISNUMBER(MATCH(P16, Bank_Transactions!H:H, 0)), "Matched in Bank", "Paid but No Bank Match")) -> Paid but No Bank Match
A17: INV2025-0016 | B17: Tri-County Services | C17: 45958 | D17: 46003 | E17: PRJ-1001 | F17: 5100-Materials | G17: 24678.73 | H17: Hillsborough | I17: 3701.8 | J17: =IF(RAND()<0.23, M17 + RANDBETWEEN(-150,150)/100, M17) -> 28380.53 | K17: TRUE | L17: 45970 | M17: 28380.53 | N17: =IF(ABS(VALUE(M17) - VALUE(J17)) > 0.01, TRUE, FALSE) -> FALSE | O17: =IF(OR(K17=FALSE, IFERROR(L17>DATE(2025,12,31), TRUE)), TRUE, FALSE) -> FALSE | P17: =B17 & "|" & (-1 * J17) -> Tri-County Services|-28380.53 | Q17: =IF(K17=FALSE, "Unpaid", IF(ISNUMBER(MATCH(P17, Bank_Transactions!H:H, 0)), "Matched in Bank", "Paid but No Bank Match")) -> Paid but No Bank Match
A18: INV2025-0017 | B18: Florida Line Crew LLC | C18: 45720 | D18: 45765 | E18: PRJ-2001 | F18: 2100-AP-Trade | G18: 17818 | H18: Pinellas | I18: 1247.26 | J18: =IF(RAND()<0.23, M18 + RANDBETWEEN(-150,150)/100, M18) -> 19065.69 | K18: TRUE | L18: 45757 | M18: 19065.26 | N18: =IF(ABS(VALUE(M18) - VALUE(J18)) > 0.01, TRUE, FALSE) -> TRUE | O18: =IF(OR(K18=FALSE, IFERROR(L18>DATE(2025,12,31), TRUE)), TRUE, FALSE) -> FALSE | P18: =B18 & "|" & (-1 * J18) -> Florida Line Crew LLC|-19065.69 | Q18: =IF(K18=FALSE, "Unpaid", IF(ISNUMBER(MATCH(P18, Bank_Transactions!H:H, 0)), "Matched in Bank", "Paid but No Bank Match")) -> Paid but No Bank Match
A19: INV2025-0018 | B19: Skyline Engineering | C19: 45918 | D19: 45963 | E19: PRJ-1002 | F19: 8900-Other | G19: 16451.39 | H19: Other_FL | I19: 1974.16 | J19: =IF(RAND()<0.23, M19 + RANDBETWEEN(-150,150)/100, M19) -> 18425.55 | K19: FALSE | M19: 18425.55 | N19: =IF(ABS(VALUE(M19) - VALUE(J19)) > 0.01, TRUE, FALSE) -> FALSE | O19: =IF(OR(K19=FALSE, IFERROR(L19>DATE(2025,12,31), TRUE)), TRUE, FALSE) -> TRUE | P19: =B19 & "|" & (-1 * J19) -> Skyline Engineering|-18425.55 | Q19: =IF(K19=FALSE, "Unpaid", IF(ISNUMBER(MATCH(P19, Bank_Transactions!H:H, 0)), "Matched in Bank", "Paid but No Bank Match")) -> Unpaid
A20: INV2025-0019 | B20: Bay Area Rentals | C20: 45858 | D20: 45903 | E20: PRJ-1002 | F20: 5200-Subcontractors | G20: 8607 | H20: Pinellas | I20: 602.49 | J20: =IF(RAND()<0.23, M20 + RANDBETWEEN(-150,150)/100, M20) -> 9209.49 | K20: TRUE | L20: 45885 | M20: 9209.49 | N20: =IF(ABS(VALUE(M20) - VALUE(J20)) > 0.01, TRUE, FALSE) -> FALSE | O20: =IF(OR(K20=FALSE, IFERROR(L20>DATE(2025,12,31), TRUE)), TRUE, FALSE) -> FALSE | P20: =B20 & "|" & (-1 * J20) -> Bay Area Rentals|-9209.49 | Q20: =IF(K20=FALSE, "Unpaid", IF(ISNUMBER(MATCH(P20, Bank_Transactions!H:H, 0)), "Matched in Bank", "Paid but No Bank Match")) -> Paid but No Bank Match
A21: INV2025-0020 | B21: Atlantic Fiber Co | C21: 45719 | D21: 45764 | E21: PRJ-4003 | F21: 5300-Equipment-Rental | G21: 18375.35 | H21: Other_FL | I21: 1102.52 | J21: =IF(RAND()<0.23, M21 + RANDBETWEEN(-150,150)/100, M21) -> 19477.87 | K21: TRUE | L21: 45758 | M21: 19477.87 | N21: =IF(ABS(VALUE(M21) - VALUE(J21)) > 0.01, TRUE, FALSE) -> FALSE | O21: =IF(OR(K21=FALSE, IFERROR(L21>DATE(2025,12,31), TRUE)), TRUE, FALSE) -> FALSE | P21: =B21 & "|" & (-1 * J21) -> Atlantic Fiber Co|-19477.87 | Q21: =IF(K21=FALSE, "Unpaid", IF(ISNUMBER(MATCH(P21, Bank_Transactions!H:H, 0)), "Matched in Bank", "Paid but No Bank Match")) -> Paid but No Bank Match
A22: INV2025-0021 | B22: Florida Line Crew LLC | C22: 45884 | D22: 45914 | E22: PRJ-1002 | F22: 5300-Equipment-Rental | G22: 17974.5 | H22: Hillsborough | I22: 1348.09 | J22: =IF(RAND()<0.23, M22 + RANDBETWEEN(-150,150)/100, M22) -> 19323.88 | K22: TRUE | L22: 45902 | M22: 19322.59 | N22: =IF(ABS(VALUE(M22) - VALUE(J22)) > 0.01, TRUE, FALSE) -> TRUE | O22: =IF(OR(K22=FALSE, IFERROR(L22>DATE(2025,12,31), TRUE)), TRUE, FALSE) -> FALSE | P22: =B22 & "|" & (-1 * J22) -> Florida Line Crew LLC|-19323.88 | Q22: =IF(K22=FALSE, "Unpaid", IF(ISNUMBER(MATCH(P22, Bank_Transactions!H:H, 0)), "Matched in Bank", "Paid but No Bank Match")) -> Paid but No Bank Match
A23: INV2025-0022 | B23: Sunline Electrical | C23: 46016 | D23: 46046 | E23: PRJ-1002 | F23: 5100-Materials | G23: 17911.24 | H23: Other_FL | I23: 1074.67 | J23: =IF(RAND()<0.23, M23 + RANDBETWEEN(-150,150)/100, M23) -> 18985.91 | K23: FALSE | M23: 18985.91 | N23: =IF(ABS(VALUE(M23) - VALUE(J23)) > 0.01, TRUE, FALSE) -> FALSE | O23: =IF(OR(K23=FALSE, IFERROR(L23>DATE(2025,12,31), TRUE)), TRUE, FALSE) -> TRUE | P23: =B23 & "|" & (-1 * J23) -> Sunline Electrical|-18985.91 | Q23: =IF(K23=FALSE, "Unpaid", IF(ISNUMBER(MATCH(P23, Bank_Transactions!H:H, 0)), "Matched in Bank", "Paid but No Bank Match")) -> Unpaid
A24: INV2025-0023 | B24: Skyline Engineering | C24: 45720 | D24: 45750 | E24: PRJ-3005 | F24: 5300-Equipment-Rental | G24: 12146.57 | H24: Other_FL | I24: 728.79 | J24: =IF(RAND()<0.23, M24 + RANDBETWEEN(-150,150)/100, M24) -> 12875.36 | K24: TRUE | L24: 45728 | M24: 12875.36 | N24: =IF(ABS(VALUE(M24) - VALUE(J24)) > 0.01, TRUE, FALSE) -> FALSE | O24: =IF(OR(K24=FALSE, IFERROR(L24>DATE(2025,12,31), TRUE)), TRUE, FALSE) -> FALSE | P24: =B24 & "|" & (-1 * J24) -> Skyline Engineering|-12875.36 | Q24: =IF(K24=FALSE, "Unpaid", IF(ISNUMBER(MATCH(P24, Bank_Transactions!H:H, 0)), "Matched in Bank", "Paid but No Bank Match")) -> Paid but No Bank Match
A25: INV2025-0024 | B25: Tidal Contractors | C25: 45879 | D25: 45924 | E25: PRJ-4003 | F25: 2100-AP-Trade | G25: 15308.23 | H25: Hillsborough | I25: 1148.12 | J25: =IF(RAND()<0.23, M25 + RANDBETWEEN(-150,150)/100, M25) -> 16456.35 | K25: TRUE | L25: 45912 | M25: 16456.35 | N25: =IF(ABS(VALUE(M25) - VALUE(J25)) > 0.01, TRUE, FALSE) -> FALSE | O25: =IF(OR(K25=FALSE, IFERROR(L25>DATE(2025,12,31), TRUE)), TRUE, FALSE) -> FALSE | P25: =B25 & "|" & (-1 * J25) -> Tidal Contractors|-16456.35 | Q25: =IF(K25=FALSE, "Unpaid", IF(ISNUMBER(MATCH(P25, Bank_Transactions!H:H, 0)), "Matched in Bank", "Paid but No Bank Match")) -> Paid but No Bank Match
A26: INV2025-0025 | B26: Tri-County Services | C26: 45693 | D26: 45738 | E26: PRJ-2001 | F26: 9999-Suspense | G26: 15172.2 | H26: Orange | I26: 986.19 | J26: =IF(RAND()<0.23, M26 + RANDBETWEEN(-150,150)/100, M26) -> 16158.39 | K26: TRUE | L26: 45725 | M26: 16158.39 | N26: =IF(ABS(VALUE(M26) - VALUE(J26)) > 0.01, TRUE, FALSE) -> FALSE | O26: =IF(OR(K26=FALSE, IFERROR(L26>DATE(2025,12,31), TRUE)), TRUE, FALSE) -> FALSE | P26: =B26 & "|" & (-1 * J26) -> Tri-County Services|-16158.39 | Q26: =IF(K26=FALSE, "Unpaid", IF(ISNUMBER(MATCH(P26, Bank_Transactions!H:H, 0)), "Matched in Bank", "Paid but No Bank Match")) -> Paid but No Bank Match
A27: INV2025-0026 | B27: Bay Area Rentals | C27: 45723 | D27: 45753 | E27: PRJ-3005 | F27: 2100-AP-Trade | G27: 7743.03 | H27: Orange | I27: 503.3 | J27: =IF(RAND()<0.23, M27 + RANDBETWEEN(-150,150)/100, M27) -> 8246.33 | K27: TRUE | L27: 45755 | M27: 8246.33 | N27: =IF(ABS(VALUE(M27) - VALUE(J27)) > 0.01, TRUE, FALSE) -> FALSE | O27: =IF(OR(K27=FALSE, IFERROR(L27>DATE(2025,12,31), TRUE)), TRUE, FALSE) -> FALSE | P27: =B27 & "|" & (-1 * J27) -> Bay Area Rentals|-8246.33 | Q27: =IF(K27=FALSE, "Unpaid", IF(ISNUMBER(MATCH(P27, Bank_Transactions!H:H, 0)), "Matched in Bank", "Paid but No Bank Match")) -> Paid but No Bank Match
A28: INV2025-0027 | B28: Tidal Contractors | C28: 45685 | D28: 45715 | E28: PRJ-4003 | F28: 2100-AP-Trade | G28: 10704.49 | H28: Orange | I28: 695.79 | J28: =IF(RAND()<0.23, M28 + RANDBETWEEN(-150,150)/100, M28) -> 11400.28 | K28: FALSE | M28: 11400.28 | N28: =IF(ABS(VALUE(M28) - VALUE(J28)) > 0.01, TRUE, FALSE) -> FALSE | O28: =IF(OR(K28=FALSE, IFERROR(L28>DATE(2025,12,31), TRUE)), TRUE, FALSE) -> TRUE | P28: =B28 & "|" & (-1 * J28) -> Tidal Contractors|-11400.28 | Q28: =IF(K28=FALSE, "Unpaid", IF(ISNUMBER(MATCH(P28, Bank_Transactions!H:H, 0)), "Matched in Bank", "Paid but No Bank Match")) -> Unpaid
A29: INV2025-0028 | B29: Tri-County Services | C29: 45785 | D29: 45815 | E29: PRJ-1002 | F29: 5200-Subcontractors | G29: 22454.24 | H29: Pinellas | I29: 1571.8 | J29: =IF(RAND()<0.23, M29 + RANDBETWEEN(-150,150)/100, M29) -> 24027.04 | K29: TRUE | L29: 45790 | M29: 24026.04 | N29: =IF(ABS(VALUE(M29) - VALUE(J29)) > 0.01, TRUE, FALSE) -> TRUE | O29: =IF(OR(K29=FALSE, IFERROR(L29>DATE(2025,12,31), TRUE)), TRUE, FALSE) -> FALSE | P29: =B29 & "|" & (-1 * J29) -> Tri-County Services|-24027.04 | Q29: =IF(K29=FALSE, "Unpaid", IF(ISNUMBER(MATCH(P29, Bank_Transactions!H:H, 0)), "Matched in Bank", "Paid but No Bank Match")) -> Paid but No Bank Match
A30: INV2025-0029 | B30: Tidal Contractors | C30: 45940 | D30: 45970 | E30: PRJ-4003 | F30: 5200-Subcontractors | G30: 20541.36 | H30: Other_FL | I30: 1232.48 | J30: =IF(RAND()<0.23, M30 + RANDBETWEEN(-150,150)/100, M30) -> 21773.17 | K30: FALSE | M30: 21773.84 | N30: =IF(ABS(VALUE(M30) - VALUE(J30)) > 0.01, TRUE, FALSE) -> TRUE | O30: =IF(OR(K30=FALSE, IFERROR(L30>DATE(2025,12,31), TRUE)), TRUE, FALSE) -> TRUE | P30: =B30 & "|" & (-1 * J30) -> Tidal Contractors|-21773.17 | Q30: =IF(K30=FALSE, "Unpaid", IF(ISNUMBER(MATCH(P30, Bank_Transactions!H:H, 0)), "Matched in Bank", "Paid but No Bank Match")) -> Unpaid
A31: INV2025-0030 | B31: Sunline Electrical | C31: 46016 | D31: 46046 | E31: PRJ-2001 | F31: 5200-Subcontractors | G31: 13585.19 | H31: Pinellas | I31: 950.96 | J31: =IF(RAND()<0.23, M31 + RANDBETWEEN(-150,150)/100, M31) -> 14535.45 | K31: FALSE | M31: 14536.15 | N31: =IF(ABS(VALUE(M31) - VALUE(J31)) > 0.01, TRUE, FALSE) -> TRUE | O31: =IF(OR(K31=FALSE, IFERROR(L31>DATE(2025,12,31), TRUE)), TRUE, FALSE) -> TRUE | P31: =B31 & "|" & (-1 * J31) -> Sunline Electrical|-14535.45 | Q31: =IF(K31=FALSE, "Unpaid", IF(ISNUMBER(MATCH(P31, Bank_Transactions!H:H, 0)), "Matched in Bank", "Paid but No Bank Match")) -> Unpaid
A32: INV2025-0031 | B32: Sunline Electrical | C32: 45891 | D32: 45921 | E32: PRJ-4003 | F32: 2100-AP-Trade | G32: 23601.29 | H32: Hillsborough | I32: 1770.1 | J32: =IF(RAND()<0.23, M32 + RANDBETWEEN(-150,150)/100, M32) -> 25371.39 | K32: TRUE | L32: 45947 | M32: 25371.39 | N32: =IF(ABS(VALUE(M32) - VALUE(J32)) > 0.01, TRUE, FALSE) -> FALSE | O32: =IF(OR(K32=FALSE, IFERROR(L32>DATE(2025,12,31), TRUE)), TRUE, FALSE) -> FALSE | P32: =B32 & "|" & (-1 * J32) -> Sunline Electrical|-25371.39 | Q32: =IF(K32=FALSE, "Unpaid", IF(ISNUMBER(MATCH(P32, Bank_Transactions!H:H, 0)), "Matched in Bank", "Paid but No Bank Match")) -> Paid but No Bank Match
A33: INV2025-0032 | B33: BrightPower Partners | C33: 45770 | D33: 45815 | E33: PRJ-1001 | F33: 5100-Materials | G33: 6720.93 | H33: Pinellas | I33: 470.47 | J33: =IF(RAND()<0.23, M33 + RANDBETWEEN(-150,150)/100, M33) -> 7191.4 | K33: TRUE | L33: 45813 | M33: 7191.4 | N33: =IF(ABS(VALUE(M33) - VALUE(J33)) > 0.01, TRUE, FALSE) -> FALSE | O33: =IF(OR(K33=FALSE, IFERROR(L33>DATE(2025,12,31), TRUE)), TRUE, FALSE) -> FALSE | P33: =B33 & "|" & (-1 * J33) -> BrightPower Partners|-7191.4 | Q33: =IF(K33=FALSE, "Unpaid", IF(ISNUMBER(MATCH(P33, Bank_Transactions!H:H, 0)), "Matched in Bank", "Paid but No Bank Match")) -> Paid but No Bank Match
A34: INV2025-0033 | B34: Tri-County Services | C34: 45770 | D34: 45815 | E34: PRJ-4003 | F34: 5100-Materials | G34: 24944.64 | H34: Orange | I34: 1621.4 | J34: =IF(RAND()<0.23, M34 + RANDBETWEEN(-150,150)/100, M34) -> 26565.24 | K34: TRUE | L34: 45776 | M34: 26566.04 | N34: =IF(ABS(VALUE(M34) - VALUE(J34)) > 0.01, TRUE, FALSE) -> TRUE | O34: =IF(OR(K34=FALSE, IFERROR(L34>DATE(2025,12,31), TRUE)), TRUE, FALSE) -> FALSE | P34: =B34 & "|" & (-1 * J34) -> Tri-County Services|-26565.24 | Q34: =IF(K34=FALSE, "Unpaid", IF(ISNUMBER(MATCH(P34, Bank_Transactions!H:H, 0)), "Matched in Bank", "Paid but No Bank Match")) -> Paid but No Bank Match
A35: INV2025-0034 | B35: Tidal Contractors | C35: 45787 | D35: 45832 | E35: PRJ-1002 | F35: 5100-Materials | G35: 1309.74 | H35: Orange | I35: 85.13 | J35: =IF(RAND()<0.23, M35 + RANDBETWEEN(-150,150)/100, M35) -> 1394.87 | K35: TRUE | L35: 45792 | M35: 1394.87 | N35: =IF(ABS(VALUE(M35) - VALUE(J35)) > 0.01, TRUE, FALSE) -> FALSE | O35: =IF(OR(K35=FALSE, IFERROR(L35>DATE(2025,12,31), TRUE)), TRUE, FALSE) -> FALSE | P35: =B35 & "|" & (-1 * J35) -> Tidal Contractors|-1394.87 | Q35: =IF(K35=FALSE, "Unpaid", IF(ISNUMBER(MATCH(P35, Bank_Transactions!H:H, 0)), "Matched in Bank", "Paid but No Bank Match")) -> Paid but No Bank Match
A36: INV2025-0035 | B36: Bay Area Rentals | C36: 45783 | D36: 45828 | E36: PRJ-3005 | F36: 5300-Equipment-Rental | G36: 12491.59 | H36: Hillsborough | I36: 936.87 | J36: =IF(RAND()<0.23, M36 + RANDBETWEEN(-150,150)/100, M36) -> 13428.46 | K36: FALSE | M36: 13428.46 | N36: =IF(ABS(VALUE(M36) - VALUE(J36)) > 0.01, TRUE, FALSE) -> FALSE | O36: =IF(OR(K36=FALSE, IFERROR(L36>DATE(2025,12,31), TRUE)), TRUE, FALSE) -> TRUE | P36: =B36 & "|" & (-1 * J36) -> Bay Area Rentals|-13428.46 | Q36: =IF(K36=FALSE, "Unpaid", IF(ISNUMBER(MATCH(P36, Bank_Transactions!H:H, 0)), "Matched in Bank", "Paid but No Bank Match")) -> Unpaid
A37: INV2025-0036 | B37: Atlantic Fiber Co | C37: 45904 | D37: 45934 | E37: PRJ-1001 | F37: 5200-Subcontractors | G37: 19159.68 | H37: Hillsborough | I37: 1436.98 | J37: =IF(RAND()<0.23, M37 + RANDBETWEEN(-150,150)/100, M37) -> 20596.66 | K37: TRUE | L37: 45946 | M37: 20596.66 | N37: =IF(ABS(VALUE(M37) - VALUE(J37)) > 0.01, TRUE, FALSE) -> FALSE | O37: =IF(OR(K37=FALSE, IFERROR(L37>DATE(2025,12,31), TRUE)), TRUE, FALSE) -> FALSE | P37: =B37 & "|" & (-1 * J37) -> Atlantic Fiber Co|-20596.66 | Q37: =IF(K37=FALSE, "Unpaid", IF(ISNUMBER(MATCH(P37, Bank_Transactions!H:H, 0)), "Matched in Bank", "Paid but No Bank Match")) -> Paid but No Bank Match
A38: INV2025-0037 | B38: Skyline Engineering | C38: 45937 | D38: 45967 | E38: PRJ-4003 | F38: 5100-Materials | G38: 24593.87 | H38: Hillsborough | I38: 1844.54 | J38: =IF(RAND()<0.23, M38 + RANDBETWEEN(-150,150)/100, M38) -> 26438.41 | K38: TRUE | L38: 45957 | M38: 26438.41 | N38: =IF(ABS(VALUE(M38) - VALUE(J38)) > 0.01, TRUE, FALSE) -> FALSE | O38: =IF(OR(K38=FALSE, IFERROR(L38>DATE(2025,12,31), TRUE)), TRUE, FALSE) -> FALSE | P38: =B38 & "|" & (-1 * J38) -> Skyline Engineering|-26438.41 | Q38: =IF(K38=FALSE, "Unpaid", IF(ISNUMBER(MATCH(P38, Bank_Transactions!H:H, 0)), "Matched in Bank", "Paid but No Bank Match")) -> Paid but No Bank Match
A39: INV2025-0038 | B39: Gulf Coast Telecom | C39: 45754 | D39: 45784 | E39: PRJ-1002 | F39: 2100-AP-Trade | G39: 12950.87 | H39: Hillsborough | I39: 971.32 | J39: =IF(RAND()<0.23, M39 + RANDBETWEEN(-150,150)/100, M39) -> 13922.19 | K39: TRUE | L39: 45761 | M39: 13922.19 | N39: =IF(ABS(VALUE(M39) - VALUE(J39)) > 0.01, TRUE, FALSE) -> FALSE | O39: =IF(OR(K39=FALSE, IFERROR(L39>DATE(2025,12,31), TRUE)), TRUE, FALSE) -> FALSE | P39: =B39 & "|" & (-1 * J39) -> Gulf Coast Telecom|-13922.19 | Q39: =IF(K39=FALSE, "Unpaid", IF(ISNUMBER(MATCH(P39, Bank_Transactions!H:H, 0)), "Matched in Bank", "Paid but No Bank Match")) -> Paid but No Bank Match
A40: INV2025-0039 | B40: Florida Line Crew LLC | C40: 45805 | D40: 45835 | E40: PRJ-4003 | F40: 5100-Materials | G40: 5895.91 | H40: Orange | I40: 383.23 | J40: =IF(RAND()<0.23, M40 + RANDBETWEEN(-150,150)/100, M40) -> 6279.14 | K40: TRUE | L40: 45828 | M40: 6279.14 | N40: =IF(ABS(VALUE(M40) - VALUE(J40)) > 0.01, TRUE, FALSE) -> FALSE | O40: =IF(OR(K40=FALSE, IFERROR(L40>DATE(2025,12,31), TRUE)), TRUE, FALSE) -> FALSE | P40: =B40 & "|" & (-1 * J40) -> Florida Line Crew LLC|-6279.14 | Q40: =IF(K40=FALSE, "Unpaid", IF(ISNUMBER(MATCH(P40, Bank_Transactions!H:H, 0)), "Matched in Bank", "Paid but No Bank Match")) -> Paid but No Bank Match
A41: INV2025-0040 | B41: Tri-County Services | C41: 45805 | D41: 45850 | E41: PRJ-1002 | F41: 5100-Materials | G41: 4771.98 | H41: Other_FL | I41: 286.32 | J41: =IF(RAND()<0.23, M41 + RANDBETWEEN(-150,150)/100, M41) -> 5058.3 | K41: TRUE | L41: 45848 | M41: 5058.3 | N41: =IF(ABS(VALUE(M41) - VALUE(J41)) > 0.01, TRUE, FALSE) -> FALSE | O41: =IF(OR(K41=FALSE, IFERROR(L41>DATE(2025,12,31), TRUE)), TRUE, FALSE) -> FALSE | P41: =B41 & "|" & (-1 * J41) -> Tri-County Services|-5058.3 | Q41: =IF(K41=FALSE, "Unpaid", IF(ISNUMBER(MATCH(P41, Bank_Transactions!H:H, 0)), "Matched in Bank", "Paid but No Bank Match")) -> Paid but No Bank Match
A42: INV2025-0041 | B42: Atlantic Fiber Co | C42: 45995 | D42: 46040 | E42: PRJ-3005 | F42: 5100-Materials | G42: 17054.41 | H42: Hillsborough | I42: 1279.08 | J42: =IF(RAND()<0.23, M42 + RANDBETWEEN(-150,150)/100, M42) -> 18332.07 | K42: FALSE | M42: 18333.49 | N42: =IF(ABS(VALUE(M42) - VALUE(J42)) > 0.01, TRUE, FALSE) -> TRUE | O42: =IF(OR(K42=FALSE, IFERROR(L42>DATE(2025,12,31), TRUE)), TRUE, FALSE) -> TRUE | P42: =B42 & "|" & (-1 * J42) -> Atlantic Fiber Co|-18332.07 | Q42: =IF(K42=FALSE, "Unpaid", IF(ISNUMBER(MATCH(P42, Bank_Transactions!H:H, 0)), "Matched in Bank", "Paid but No Bank Match")) -> Unpaid
A43: INV2025-0042 | B43: Gulf Coast Telecom | C43: 45808 | D43: 45853 | E43: PRJ-2001 | F43: 5300-Equipment-Rental | G43: 17546.72 | H43: Other_FL | I43: 1052.8 | J43: =IF(RAND()<0.23, M43 + RANDBETWEEN(-150,150)/100, M43) -> 18599.81 | K43: TRUE | L43: 45828 | M43: 18599.52 | N43: =IF(ABS(VALUE(M43) - VALUE(J43)) > 0.01, TRUE, FALSE) -> TRUE | O43: =IF(OR(K43=FALSE, IFERROR(L43>DATE(2025,12,31), TRUE)), TRUE, FALSE) -> FALSE | P43: =B43 & "|" & (-1 * J43) -> Gulf Coast Telecom|-18599.81 | Q43: =IF(K43=FALSE, "Unpaid", IF(ISNUMBER(MATCH(P43, Bank_Transactions!H:H, 0)), "Matched in Bank", "Paid but No Bank Match")) -> Paid but No Bank Match
A44: INV2025-0043 | B44: Sunshine Equipment | C44: 46003 | D44: 46033 | E44: PRJ-1001 | F44: 9999-Suspense | G44: 13157.58 | H44: Other_FL | I44: 789.45 | J44: =IF(RAND()<0.23, M44 + RANDBETWEEN(-150,150)/100, M44) -> 13947.03 | K44: TRUE | L44: 46008 | M44: 13947.03 | N44: =IF(ABS(VALUE(M44) - VALUE(J44)) > 0.01, TRUE, FALSE) -> FALSE | O44: =IF(OR(K44=FALSE, IFERROR(L44>DATE(2025,12,31), TRUE)), TRUE, FALSE) -> FALSE | P44: =B44 & "|" & (-1 * J44) -> Sunshine Equipment|-13947.03 | Q44: =IF(K44=FALSE, "Unpaid", IF(ISNUMBER(MATCH(P44, Bank_Transactions!H:H, 0)), "Matched in Bank", "Paid but No Bank Match")) -> Paid but No Bank Match
A45: INV2025-0044 | B45: BrightPower Partners | C45: 45961 | D45: 46006 | E45: PRJ-1001 | F45: 9999-Suspense | G45: 14178.19 | H45: Pinellas | I45: 992.47 | J45: =IF(RAND()<0.23, M45 + RANDBETWEEN(-150,150)/100, M45) -> 15170.66 | K45: FALSE | M45: 15170.66 | N45: =IF(ABS(VALUE(M45) - VALUE(J45)) > 0.01, TRUE, FALSE) -> FALSE | O45: =IF(OR(K45=FALSE, IFERROR(L45>DATE(2025,12,31), TRUE)), TRUE, FALSE) -> TRUE | P45: =B45 & "|" & (-1 * J45) -> BrightPower Partners|-15170.66 | Q45: =IF(K45=FALSE, "Unpaid", IF(ISNUMBER(MATCH(P45, Bank_Transactions!H:H, 0)), "Matched in Bank", "Paid but No Bank Match")) -> Unpaid
A46: INV2025-0045 | B46: Atlantic Fiber Co | C46: 45666 | D46: 45711 | E46: PRJ-1002 | F46: 5300-Equipment-Rental | G46: 17658.77 | H46: Pinellas | I46: 1236.11 | J46: =IF(RAND()<0.23, M46 + RANDBETWEEN(-150,150)/100, M46) -> 18895.86 | K46: TRUE | L46: 45690 | M46: 18894.88 | N46: =IF(ABS(VALUE(M46) - VALUE(J46)) > 0.01, TRUE, FALSE) -> TRUE | O46: =IF(OR(K46=FALSE, IFERROR(L46>DATE(2025,12,31), TRUE)), TRUE, FALSE) -> FALSE | P46: =B46 & "|" & (-1 * J46) -> Atlantic Fiber Co|-18895.86 | Q46: =IF(K46=FALSE, "Unpaid", IF(ISNUMBER(MATCH(P46, Bank_Transactions!H:H, 0)), "Matched in Bank", "Paid but No Bank Match")) -> Paid but No Bank Match
A47: INV2025-0046 | B47: Peak Materials Supply | C47: 45809 | D47: 45854 | E47: PRJ-1002 | F47: 2100-AP-Trade | G47: 22250.37 | H47: Other_FL | I47: 1335.02 | J47: =IF(RAND()<0.23, M47 + RANDBETWEEN(-150,150)/100, M47) -> 23585.11 | K47: FALSE | M47: 23585.39 | N47: =IF(ABS(VALUE(M47) - VALUE(J47)) > 0.01, TRUE, FALSE) -> TRUE | O47: =IF(OR(K47=FALSE, IFERROR(L47>DATE(2025,12,31), TRUE)), TRUE, FALSE) -> TRUE | P47: =B47 & "|" & (-1 * J47) -> Peak Materials Supply|-23585.11 | Q47: =IF(K47=FALSE, "Unpaid", IF(ISNUMBER(MATCH(P47, Bank_Transactions!H:H, 0)), "Matched in Bank", "Paid but No Bank Match")) -> Unpaid
A48: INV2025-0047 | B48: Tidal Contractors | C48: 45770 | D48: 45800 | E48: PRJ-1001 | F48: 2100-AP-Trade | G48: 22514.58 | H48: Hillsborough | I48: 1688.59 | J48: =IF(RAND()<0.23, M48 + RANDBETWEEN(-150,150)/100, M48) -> 24203.43 | K48: TRUE | L48: 45799 | M48: 24203.17 | N48: =IF(ABS(VALUE(M48) - VALUE(J48)) > 0.01, TRUE, FALSE) -> TRUE | O48: =IF(OR(K48=FALSE, IFERROR(L48>DATE(2025,12,31), TRUE)), TRUE, FALSE) -> FALSE | P48: =B48 & "|" & (-1 * J48) -> Tidal Contractors|-24203.43 | Q48: =IF(K48=FALSE, "Unpaid", IF(ISNUMBER(MATCH(P48, Bank_Transactions!H:H, 0)), "Matched in Bank", "Paid but No Bank Match")) -> Paid but No Bank Match
A49: INV2025-0048 | B49: Atlantic Fiber Co | C49: 46006 | D49: 46036 | E49: PRJ-3005 | F49: 5300-Equipment-Rental | G49: 7981.41 | H49: Other_FL | I49: 478.88 | J49: =IF(RAND()<0.23, M49 + RANDBETWEEN(-150,150)/100, M49) -> 8460.29 | K49: FALSE | M49: 8460.29 | N49: =IF(ABS(VALUE(M49) - VALUE(J49)) > 0.01, TRUE, FALSE) -> FALSE | O49: =IF(OR(K49=FALSE, IFERROR(L49>DATE(2025,12,31), TRUE)), TRUE, FALSE) -> TRUE | P49: =B49 & "|" & (-1 * J49) -> Atlantic Fiber Co|-8460.29 | Q49: =IF(K49=FALSE, "Unpaid", IF(ISNUMBER(MATCH(P49, Bank_Transactions!H:H, 0)), "Matched in Bank", "Paid but No Bank Match")) -> Unpaid
A50: INV2025-0049 | B50: Atlantic Fiber Co | C50: 45865 | D50: 45910 | E50: PRJ-1001 | F50: 9999-Suspense | G50: 4810.17 | H50: Other_FL | I50: 288.61 | J50: =IF(RAND()<0.23, M50 + RANDBETWEEN(-150,150)/100, M50) -> 5098.78 | K50: TRUE | L50: 45883 | M50: 5098.78 | N50: =IF(ABS(VALUE(M50) - VALUE(J50)) > 0.01, TRUE, FALSE) -> FALSE | O50: =IF(OR(K50=FALSE, IFERROR(L50>DATE(2025,12,31), TRUE)), TRUE, FALSE) -> FALSE | P50: =B50 & "|" & (-1 * J50) -> Atlantic Fiber Co|-5098.78 | Q50: =IF(K50=FALSE, "Unpaid", IF(ISNUMBER(MATCH(P50, Bank_Transactions!H:H, 0)), "Matched in Bank", "Paid but No Bank Match")) -> Paid but No Bank Match
A51: INV2025-0050 | B51: Sunline Electrical | C51: 45934 | D51: 45979 | E51: PRJ-2001 | F51: 5300-Equipment-Rental | G51: 9478.49 | H51: Orange | I51: 616.1 | J51: =IF(RAND()<0.23, M51 + RANDBETWEEN(-150,150)/100, M51) -> 10094.59 | K51: TRUE | L51: 45955 | M51: 10094.59 | N51: =IF(ABS(VALUE(M51) - VALUE(J51)) > 0.01, TRUE, FALSE) -> FALSE | O51: =IF(OR(K51=FALSE, IFERROR(L51>DATE(2025,12,31), TRUE)), TRUE, FALSE) -> FALSE | P51: =B51 & "|" & (-1 * J51) -> Sunline Electrical|-10094.59 | Q51: =IF(K51=FALSE, "Unpaid", IF(ISNUMBER(MATCH(P51, Bank_Transactions!H:H, 0)), "Matched in Bank", "Paid but No Bank Match")) -> Paid but No Bank Match
A52: INV2025-0051 | B52: Bay Area Rentals | C52: 45785 | D52: 45830 | E52: PRJ-1002 | F52: 5100-Materials | G52: 2795.03 | H52: Orange | I52: 181.68 | J52: =IF(RAND()<0.23, M52 + RANDBETWEEN(-150,150)/100, M52) -> 2976.71 | K52: TRUE | L52: 45811 | M52: 2976.71 | N52: =IF(ABS(VALUE(M52) - VALUE(J52)) > 0.01, TRUE, FALSE) -> FALSE | O52: =IF(OR(K52=FALSE, IFERROR(L52>DATE(2025,12,31), TRUE)), TRUE, FALSE) -> FALSE | P52: =B52 & "|" & (-1 * J52) -> Bay Area Rentals|-2976.71 | Q52: =IF(K52=FALSE, "Unpaid", IF(ISNUMBER(MATCH(P52, Bank_Transactions!H:H, 0)), "Matched in Bank", "Paid but No Bank Match")) -> Paid but No Bank Match
A53: INV2025-0052 | B53: Atlantic Fiber Co | C53: 45895 | D53: 45925 | E53: PRJ-4003 | F53: 2100-AP-Trade | G53: 24482.88 | H53: Orange | I53: 1591.39 | J53: =IF(RAND()<0.23, M53 + RANDBETWEEN(-150,150)/100, M53) -> 26074.27 | K53: TRUE | L53: 45907 | M53: 26074.27 | N53: =IF(ABS(VALUE(M53) - VALUE(J53)) > 0.01, TRUE, FALSE) -> FALSE | O53: =IF(OR(K53=FALSE, IFERROR(L53>DATE(2025,12,31), TRUE)), TRUE, FALSE) -> FALSE | P53: =B53 & "|" & (-1 * J53) -> Atlantic Fiber Co|-26074.27 | Q53: =IF(K53=FALSE, "Unpaid", IF(ISNUMBER(MATCH(P53, Bank_Transactions!H:H, 0)), "Matched in Bank", "Paid but No Bank Match")) -> Paid but No Bank Match
A54: INV2025-0053 | B54: Sunline Electrical | C54: 45940 | D54: 45970 | E54: PRJ-4003 | F54: 5300-Equipment-Rental | G54: 9076.92 | H54: Pinellas | I54: 635.38 | J54: =IF(RAND()<0.23, M54 + RANDBETWEEN(-150,150)/100, M54) -> 9712.52 | K54: TRUE | L54: 46008 | M54: 9712.3 | N54: =IF(ABS(VALUE(M54) - VALUE(J54)) > 0.01, TRUE, FALSE) -> TRUE | O54: =IF(OR(K54=FALSE, IFERROR(L54>DATE(2025,12,31), TRUE)), TRUE, FALSE) -> FALSE | P54: =B54 & "|" & (-1 * J54) -> Sunline Electrical|-9712.52 | Q54: =IF(K54=FALSE, "Unpaid", IF(ISNUMBER(MATCH(P54, Bank_Transactions!H:H, 0)), "Matched in Bank", "Paid but No Bank Match")) -> Paid but No Bank Match
A55: INV2025-0054 | B55: Sunline Electrical | C55: 45974 | D55: 46004 | E55: PRJ-1002 | F55: 2100-AP-Trade | G55: 14514.1 | H55: Hillsborough | I55: 1088.56 | J55: =IF(RAND()<0.23, M55 + RANDBETWEEN(-150,150)/100, M55) -> 15602.66 | K55: TRUE | L55: 45995 | M55: 15602.66 | N55: =IF(ABS(VALUE(M55) - VALUE(J55)) > 0.01, TRUE, FALSE) -> FALSE | O55: =IF(OR(K55=FALSE, IFERROR(L55>DATE(2025,12,31), TRUE)), TRUE, FALSE) -> FALSE | P55: =B55 & "|" & (-1 * J55) -> Sunline Electrical|-15602.66 | Q55: =IF(K55=FALSE, "Unpaid", IF(ISNUMBER(MATCH(P55, Bank_Transactions!H:H, 0)), "Matched in Bank", "Paid but No Bank Match")) -> Paid but No Bank Match
A56: INV2025-0055 | B56: Tri-County Services | C56: 45829 | D56: 45859 | E56: PRJ-3005 | F56: 9999-Suspense | G56: 23871.25 | H56: Pinellas | I56: 1670.99 | J56: =IF(RAND()<0.23, M56 + RANDBETWEEN(-150,150)/100, M56) -> 25542.24 | K56: FALSE | M56: 25542.24 | N56: =IF(ABS(VALUE(M56) - VALUE(J56)) > 0.01, TRUE, FALSE) -> FALSE | O56: =IF(OR(K56=FALSE, IFERROR(L56>DATE(2025,12,31), TRUE)), TRUE, FALSE) -> TRUE | P56: =B56 & "|" & (-1 * J56) -> Tri-County Services|-25542.24 | Q56: =IF(K56=FALSE, "Unpaid", IF(ISNUMBER(MATCH(P56, Bank_Transactions!H:H, 0)), "Matched in Bank", "Paid but No Bank Match")) -> Unpaid
A57: INV2025-0056 | B57: Skyline Engineering | C57: 45756 | D57: 45786 | E57: PRJ-4003 | F57: 2100-AP-Trade | G57: 23850.26 | H57: Other_FL | I57: 1431.02 | J57: =IF(RAND()<0.23, M57 + RANDBETWEEN(-150,150)/100, M57) -> 25281.28 | K57: TRUE | L57: 45806 | M57: 25281.28 | N57: =IF(ABS(VALUE(M57) - VALUE(J57)) > 0.01, TRUE, FALSE) -> FALSE | O57: =IF(OR(K57=FALSE, IFERROR(L57>DATE(2025,12,31), TRUE)), TRUE, FALSE) -> FALSE | P57: =B57 & "|" & (-1 * J57) -> Skyline Engineering|-25281.28 | Q57: =IF(K57=FALSE, "Unpaid", IF(ISNUMBER(MATCH(P57, Bank_Transactions!H:H, 0)), "Matched in Bank", "Paid but No Bank Match")) -> Paid but No Bank Match
A58: INV2025-0057 | B58: Tri-County Services | C58: 45838 | D58: 45883 | E58: PRJ-2001 | F58: 5100-Materials | G58: 24518.12 | H58: Orange | I58: 1593.68 | J58: =IF(RAND()<0.23, M58 + RANDBETWEEN(-150,150)/100, M58) -> 26110.5 | K58: TRUE | L58: 45874 | M58: 26111.8 | N58: =IF(ABS(VALUE(M58) - VALUE(J58)) > 0.01, TRUE, FALSE) -> TRUE | O58: =IF(OR(K58=FALSE, IFERROR(L58>DATE(2025,12,31), TRUE)), TRUE, FALSE) -> FALSE | P58: =B58 & "|" & (-1 * J58) -> Tri-County Services|-26110.5 | Q58: =IF(K58=FALSE, "Unpaid", IF(ISNUMBER(MATCH(P58, Bank_Transactions!H:H, 0)), "Matched in Bank", "Paid but No Bank Match")) -> Paid but No Bank Match
A59: INV2025-0058 | B59: Atlantic Fiber Co | C59: 45818 | D59: 45863 | E59: PRJ-3005 | F59: 5100-Materials | G59: 4652.57 | H59: Orange | I59: 302.42 | J59: =IF(RAND()<0.23, M59 + RANDBETWEEN(-150,150)/100, M59) -> 4954.99 | K59: TRUE | L59: 45876 | M59: 4954.99 | N59: =IF(ABS(VALUE(M59) - VALUE(J59)) > 0.01, TRUE, FALSE) -> FALSE | O59: =IF(OR(K59=FALSE, IFERROR(L59>DATE(2025,12,31), TRUE)), TRUE, FALSE) -> FALSE | P59: =B59 & "|" & (-1 * J59) -> Atlantic Fiber Co|-4954.99 | Q59: =IF(K59=FALSE, "Unpaid", IF(ISNUMBER(MATCH(P59, Bank_Transactions!H:H, 0)), "Matched in Bank", "Paid but No Bank Match")) -> Paid but No Bank Match
A60: INV2025-0059 | B60: Sunshine Equipment | C60: 45715 | D60: 45760 | E60: PRJ-1001 | F60: 9999-Suspense | G60: 2225.2 | H60: Other_FL | I60: 133.51 | J60: =IF(RAND()<0.23, M60 + RANDBETWEEN(-150,150)/100, M60) -> 2358.13 | K60: TRUE | L60: 45766 | M60: 2358.71 | N60: =IF(ABS(VALUE(M60) - VALUE(J60)) > 0.01, TRUE, FALSE) -> TRUE | O60: =IF(OR(K60=FALSE, IFERROR(L60>DATE(2025,12,31), TRUE)), TRUE, FALSE) -> FALSE | P60: =B60 & "|" & (-1 * J60) -> Sunshine Equipment|-2358.13 | Q60: =IF(K60=FALSE, "Unpaid", IF(ISNUMBER(MATCH(P60, Bank_Transactions!H:H, 0)), "Matched in Bank", "Paid but No Bank Match")) -> Paid but No Bank Match
A61: INV2025-0060 | B61: Skyline Engineering | C61: 45999 | D61: 46029 | E61: PRJ-1001 | F61: 5100-Materials | G61: 6727.01 | H61: Orange | I61: 437.26 | J61: =IF(RAND()<0.23, M61 + RANDBETWEEN(-150,150)/100, M61) -> 7162.88 | K61: TRUE | L61: 46020 | M61: 7164.27 | N61: =IF(ABS(VALUE(M61) - VALUE(J61)) > 0.01, TRUE, FALSE) -> TRUE | O61: =IF(OR(K61=FALSE, IFERROR(L61>DATE(2025,12,31), TRUE)), TRUE, FALSE) -> FALSE | P61: =B61 & "|" & (-1 * J61) -> Skyline Engineering|-7162.88 | Q61: =IF(K61=FALSE, "Unpaid", IF(ISNUMBER(MATCH(P61, Bank_Transactions!H:H, 0)), "Matched in Bank", "Paid but No Bank Match")) -> Paid but No Bank Match
A62: INV2025-0061 | B62: Tampa Grid Services | C62: 45761 | D62: 45806 | E62: PRJ-1001 | F62: 5100-Materials | G62: 17710.86 | H62: Orange | I62: 1151.21 | J62: =IF(RAND()<0.23, M62 + RANDBETWEEN(-150,150)/100, M62) -> 18862.07 | K62: TRUE | L62: 45807 | M62: 18862.07 | N62: =IF(ABS(VALUE(M62) - VALUE(J62)) > 0.01, TRUE, FALSE) -> FALSE | O62: =IF(OR(K62=FALSE, IFERROR(L62>DATE(2025,12,31), TRUE)), TRUE, FALSE) -> FALSE | P62: =B62 & "|" & (-1 * J62) -> Tampa Grid Services|-18862.07 | Q62: =IF(K62=FALSE, "Unpaid", IF(ISNUMBER(MATCH(P62, Bank_Transactions!H:H, 0)), "Matched in Bank", "Paid but No Bank Match")) -> Paid but No Bank Match
A63: INV2025-0062 | B63: Peak Materials Supply | C63: 45904 | D63: 45934 | E63: PRJ-3005 | F63: 5200-Subcontractors | G63: 6777.07 | H63: Hillsborough | I63: 508.28 | J63: =IF(RAND()<0.23, M63 + RANDBETWEEN(-150,150)/100, M63) -> 7285.78 | K63: TRUE | L63: 45968 | M63: 7285.35 | N63: =IF(ABS(VALUE(M63) - VALUE(J63)) > 0.01, TRUE, FALSE) -> TRUE | O63: =IF(OR(K63=FALSE, IFERROR(L63>DATE(2025,12,31), TRUE)), TRUE, FALSE) -> FALSE | P63: =B63 & "|" & (-1 * J63) -> Peak Materials Supply|-7285.78 | Q63: =IF(K63=FALSE, "Unpaid", IF(ISNUMBER(MATCH(P63, Bank_Transactions!H:H, 0)), "Matched in Bank", "Paid but No Bank Match")) -> Paid but No Bank Match
A64: INV2025-0063 | B64: Tri-County Services | C64: 45970 | D64: 46015 | E64: PRJ-1001 | F64: 5100-Materials | G64: 5259.71 | H64: Orange | I64: 341.88 | J64: =IF(RAND()<0.23, M64 + RANDBETWEEN(-150,150)/100, M64) -> 5601.59 | K64: TRUE | L64: 45990 | M64: 5601.59 | N64: =IF(ABS(VALUE(M64) - VALUE(J64)) > 0.01, TRUE, FALSE) -> FALSE | O64: =IF(OR(K64=FALSE, IFERROR(L64>DATE(2025,12,31), TRUE)), TRUE, FALSE) -> FALSE | P64: =B64 & "|" & (-1 * J64) -> Tri-County Services|-5601.59 | Q64: =IF(K64=FALSE, "Unpaid", IF(ISNUMBER(MATCH(P64, Bank_Transactions!H:H, 0)), "Matched in Bank", "Paid but No Bank Match")) -> Paid but No Bank Match
A65: INV2025-0064 | B65: Gulf Coast Telecom | C65: 45799 | D65: 45829 | E65: PRJ-4003 | F65: 5100-Materials | G65: 8780.88 | H65: Orange | I65: 570.76 | J65: =IF(RAND()<0.23, M65 + RANDBETWEEN(-150,150)/100, M65) -> 9351.64 | K65: TRUE | L65: 45835 | M65: 9351.64 | N65: =IF(ABS(VALUE(M65) - VALUE(J65)) > 0.01, TRUE, FALSE) -> FALSE | O65: =IF(OR(K65=FALSE, IFERROR(L65>DATE(2025,12,31), TRUE)), TRUE, FALSE) -> FALSE | P65: =B65 & "|" & (-1 * J65) -> Gulf Coast Telecom|-9351.64 | Q65: =IF(K65=FALSE, "Unpaid", IF(ISNUMBER(MATCH(P65, Bank_Transactions!H:H, 0)), "Matched in Bank", "Paid but No Bank Match")) -> Paid but No Bank Match
A66: INV2025-0065 | B66: Peak Materials Supply | C66: 45872 | D66: 45902 | E66: PRJ-2001 | F66: 5100-Materials | G66: 8539.74 | H66: Orange | I66: 555.08 | J66: =IF(RAND()<0.23, M66 + RANDBETWEEN(-150,150)/100, M66) -> 9094.82 | K66: TRUE | L66: 45938 | M66: 9094.82 | N66: =IF(ABS(VALUE(M66) - VALUE(J66)) > 0.01, TRUE, FALSE) -> FALSE | O66: =IF(OR(K66=FALSE, IFERROR(L66>DATE(2025,12,31), TRUE)), TRUE, FALSE) -> FALSE | P66: =B66 & "|" & (-1 * J66) -> Peak Materials Supply|-9094.82 | Q66: =IF(K66=FALSE, "Unpaid", IF(ISNUMBER(MATCH(P66, Bank_Transactions!H:H, 0)), "Matched in Bank", "Paid but No Bank Match")) -> Paid but No Bank Match
A67: INV2025-0066 | B67: Tidal Contractors | C67: 45782 | D67: 45827 | E67: PRJ-2001 | F67: 2100-AP-Trade | G67: 21579.91 | H67: Hillsborough | I67: 1618.49 | J67: =IF(RAND()<0.23, M67 + RANDBETWEEN(-150,150)/100, M67) -> 23197 | K67: TRUE | L67: 45828 | M67: 23198.4 | N67: =IF(ABS(VALUE(M67) - VALUE(J67)) > 0.01, TRUE, FALSE) -> TRUE | O67: =IF(OR(K67=FALSE, IFERROR(L67>DATE(2025,12,31), TRUE)), TRUE, FALSE) -> FALSE | P67: =B67 & "|" & (-1 * J67) -> Tidal Contractors|-23197 | Q67: =IF(K67=FALSE, "Unpaid", IF(ISNUMBER(MATCH(P67, Bank_Transactions!H:H, 0)), "Matched in Bank", "Paid but No Bank Match")) -> Paid but No Bank Match
A68: INV2025-0067 | B68: Tri-County Services | C68: 45983 | D68: 46028 | E68: PRJ-2001 | F68: 2100-AP-Trade | G68: 13658.52 | H68: Hillsborough | I68: 1024.39 | J68: =IF(RAND()<0.23, M68 + RANDBETWEEN(-150,150)/100, M68) -> 14682.91 | K68: TRUE | L68: 45995 | M68: 14682.91 | N68: =IF(ABS(VALUE(M68) - VALUE(J68)) > 0.01, TRUE, FALSE) -> FALSE | O68: =IF(OR(K68=FALSE, IFERROR(L68>DATE(2025,12,31), TRUE)), TRUE, FALSE) -> FALSE | P68: =B68 & "|" & (-1 * J68) -> Tri-County Services|-14682.91 | Q68: =IF(K68=FALSE, "Unpaid", IF(ISNUMBER(MATCH(P68, Bank_Transactions!H:H, 0)), "Matched in Bank", "Paid but No Bank Match")) -> Paid but No Bank Match
A69: INV2025-0068 | B69: Florida Line Crew LLC | C69: 45710 | D69: 45740 | E69: PRJ-2001 | F69: 5100-Materials | G69: 24148.67 | H69: Other_FL | I69: 1448.92 | J69: =IF(RAND()<0.23, M69 + RANDBETWEEN(-150,150)/100, M69) -> 25597.59 | K69: TRUE | L69: 45720 | M69: 25597.59 | N69: =IF(ABS(VALUE(M69) - VALUE(J69)) > 0.01, TRUE, FALSE) -> FALSE | O69: =IF(OR(K69=FALSE, IFERROR(L69>DATE(2025,12,31), TRUE)), TRUE, FALSE) -> FALSE | P69: =B69 & "|" & (-1 * J69) -> Florida Line Crew LLC|-25597.59 | Q69: =IF(K69=FALSE, "Unpaid", IF(ISNUMBER(MATCH(P69, Bank_Transactions!H:H, 0)), "Matched in Bank", "Paid but No Bank Match")) -> Paid but No Bank Match
A70: INV2025-0069 | B70: Tidal Contractors | C70: 46022 | D70: 46067 | E70: PRJ-4003 | F70: 2100-AP-Trade | G70: 10578.17 | H70: Hillsborough | I70: 793.36 | J70: =IF(RAND()<0.23, M70 + RANDBETWEEN(-150,150)/100, M70) -> 11370.83 | K70: FALSE | M70: 11371.53 | N70: =IF(ABS(VALUE(M70) - VALUE(J70)) > 0.01, TRUE, FALSE) -> TRUE | O70: =IF(OR(K70=FALSE, IFERROR(L70>DATE(2025,12,31), TRUE)), TRUE, FALSE) -> TRUE | P70: =B70 & "|" & (-1 * J70) -> Tidal Contractors|-11370.83 | Q70: =IF(K70=FALSE, "Unpaid", IF(ISNUMBER(MATCH(P70, Bank_Transactions!H:H, 0)), "Matched in Bank", "Paid but No Bank Match")) -> Unpaid
A71: INV2025-0070 | B71: Gulf Coast Telecom | C71: 45965 | D71: 45995 | E71: PRJ-4003 | F71: 2100-AP-Trade | G71: 24253.65 | H71: Orange | I71: 1576.49 | J71: =IF(RAND()<0.23, M71 + RANDBETWEEN(-150,150)/100, M71) -> 25830.14 | K71: TRUE | L71: 45988 | M71: 25830.14 | N71: =IF(ABS(VALUE(M71) - VALUE(J71)) > 0.01, TRUE, FALSE) -> FALSE | O71: =IF(OR(K71=FALSE, IFERROR(L71>DATE(2025,12,31), TRUE)), TRUE, FALSE) -> FALSE | P71: =B71 & "|" & (-1 * J71) -> Gulf Coast Telecom|-25830.14 | Q71: =IF(K71=FALSE, "Unpaid", IF(ISNUMBER(MATCH(P71, Bank_Transactions!H:H, 0)), "Matched in Bank", "Paid but No Bank Match")) -> Paid but No Bank Match
A72: INV2025-0071 | B72: Skyline Engineering | C72: 45802 | D72: 45832 | E72: PRJ-3005 | F72: 5100-Materials | G72: 11121.26 | H72: Hillsborough | I72: 834.09 | J72: =IF(RAND()<0.23, M72 + RANDBETWEEN(-150,150)/100, M72) -> 11955.35 | K72: TRUE | L72: 45868 | M72: 11955.35 | N72: =IF(ABS(VALUE(M72) - VALUE(J72)) > 0.01, TRUE, FALSE) -> FALSE | O72: =IF(OR(K72=FALSE, IFERROR(L72>DATE(2025,12,31), TRUE)), TRUE, FALSE) -> FALSE | P72: =B72 & "|" & (-1 * J72) -> Skyline Engineering|-11955.35 | Q72: =IF(K72=FALSE, "Unpaid", IF(ISNUMBER(MATCH(P72, Bank_Transactions!H:H, 0)), "Matched in Bank", "Paid but No Bank Match")) -> Paid but No Bank Match
A73: INV2025-0072 | B73: Peak Materials Supply | C73: 45936 | D73: 45981 | E73: PRJ-1001 | F73: 5200-Subcontractors | G73: 17368.25 | H73: Pinellas | I73: 1215.78 | J73: =IF(RAND()<0.23, M73 + RANDBETWEEN(-150,150)/100, M73) -> 18584.03 | K73: TRUE | L73: 45941 | M73: 18584.03 | N73: =IF(ABS(VALUE(M73) - VALUE(J73)) > 0.01, TRUE, FALSE) -> FALSE | O73: =IF(OR(K73=FALSE, IFERROR(L73>DATE(2025,12,31), TRUE)), TRUE, FALSE) -> FALSE | P73: =B73 & "|" & (-1 * J73) -> Peak Materials Supply|-18584.03 | Q73: =IF(K73=FALSE, "Unpaid", IF(ISNUMBER(MATCH(P73, Bank_Transactions!H:H, 0)), "Matched in Bank", "Paid but No Bank Match")) -> Paid but No Bank Match
A74: INV2025-0073 | B74: Tri-County Services | C74: 45896 | D74: 45926 | E74: PRJ-1001 | F74: 5200-Subcontractors | G74: 13956.05 | H74: Other_FL | I74: 837.36 | J74: =IF(RAND()<0.23, M74 + RANDBETWEEN(-150,150)/100, M74) -> 14793.41 | K74: TRUE | L74: 45901 | M74: 14793.41 | N74: =IF(ABS(VALUE(M74) - VALUE(J74)) > 0.01, TRUE, FALSE) -> FALSE | O74: =IF(OR(K74=FALSE, IFERROR(L74>DATE(2025,12,31), TRUE)), TRUE, FALSE) -> FALSE | P74: =B74 & "|" & (-1 * J74) -> Tri-County Services|-14793.41 | Q74: =IF(K74=FALSE, "Unpaid", IF(ISNUMBER(MATCH(P74, Bank_Transactions!H:H, 0)), "Matched in Bank", "Paid but No Bank Match")) -> Paid but No Bank Match
A75: INV2025-0074 | B75: Skyline Engineering | C75: 45929 | D75: 45959 | E75: PRJ-1002 | F75: 5100-Materials | G75: 16599.23 | H75: Pinellas | I75: 1161.95 | J75: =IF(RAND()<0.23, M75 + RANDBETWEEN(-150,150)/100, M75) -> 17761.18 | K75: TRUE | L75: 45959 | M75: 17761.18 | N75: =IF(ABS(VALUE(M75) - VALUE(J75)) > 0.01, TRUE, FALSE) -> FALSE | O75: =IF(OR(K75=FALSE, IFERROR(L75>DATE(2025,12,31), TRUE)), TRUE, FALSE) -> FALSE | P75: =B75 & "|" & (-1 * J75) -> Skyline Engineering|-17761.18 | Q75: =IF(K75=FALSE, "Unpaid", IF(ISNUMBER(MATCH(P75, Bank_Transactions!H:H, 0)), "Matched in Bank", "Paid but No Bank Match")) -> Paid but No Bank Match
A76: INV2025-0075 | B76: Bay Area Rentals | C76: 45801 | D76: 45831 | E76: PRJ-1002 | F76: 5200-Subcontractors | G76: 3444.03 | H76: Other_FL | I76: 206.64 | J76: =IF(RAND()<0.23, M76 + RANDBETWEEN(-150,150)/100, M76) -> 3650.67 | K76: TRUE | L76: 45852 | M76: 3650.67 | N76: =IF(ABS(VALUE(M76) - VALUE(J76)) > 0.01, TRUE, FALSE) -> FALSE | O76: =IF(OR(K76=FALSE, IFERROR(L76>DATE(2025,12,31), TRUE)), TRUE, FALSE) -> FALSE | P76: =B76 & "|" & (-1 * J76) -> Bay Area Rentals|-3650.67 | Q76: =IF(K76=FALSE, "Unpaid", IF(ISNUMBER(MATCH(P76, Bank_Transactions!H:H, 0)), "Matched in Bank", "Paid but No Bank Match")) -> Paid but No Bank Match
A77: INV2025-0076 | B77: Tri-County Services | C77: 45751 | D77: 45781 | E77: PRJ-2001 | F77: 5100-Materials | G77: 17739.62 | H77: Hillsborough | I77: 1330.47 | J77: =IF(RAND()<0.23, M77 + RANDBETWEEN(-150,150)/100, M77) -> 19070.09 | K77: TRUE | L77: 45803 | M77: 19070.09 | N77: =IF(ABS(VALUE(M77) - VALUE(J77)) > 0.01, TRUE, FALSE) -> FALSE | O77: =IF(OR(K77=FALSE, IFERROR(L77>DATE(2025,12,31), TRUE)), TRUE, FALSE) -> FALSE | P77: =B77 & "|" & (-1 * J77) -> Tri-County Services|-19070.09 | Q77: =IF(K77=FALSE, "Unpaid", IF(ISNUMBER(MATCH(P77, Bank_Transactions!H:H, 0)), "Matched in Bank", "Paid but No Bank Match")) -> Paid but No Bank Match
A78: INV2025-0077 | B78: Bay Area Rentals | C78: 45998 | D78: 46028 | E78: PRJ-3005 | F78: 5100-Materials | G78: 4743.45 | H78: Pinellas | I78: 332.04 | J78: =IF(RAND()<0.23, M78 + RANDBETWEEN(-150,150)/100, M78) -> 5075.49 | K78: FALSE | M78: 5075.49 | N78: =IF(ABS(VALUE(M78) - VALUE(J78)) > 0.01, TRUE, FALSE) -> FALSE | O78: =IF(OR(K78=FALSE, IFERROR(L78>DATE(2025,12,31), TRUE)), TRUE, FALSE) -> TRUE | P78: =B78 & "|" & (-1 * J78) -> Bay Area Rentals|-5075.49 | Q78: =IF(K78=FALSE, "Unpaid", IF(ISNUMBER(MATCH(P78, Bank_Transactions!H:H, 0)), "Matched in Bank", "Paid but No Bank Match")) -> Unpaid
A79: INV2025-0078 | B79: Sunshine Equipment | C79: 45907 | D79: 45952 | E79: PRJ-2001 | F79: 5100-Materials | G79: 16059.79 | H79: Pinellas | I79: 1124.19 | J79: =IF(RAND()<0.23, M79 + RANDBETWEEN(-150,150)/100, M79) -> 17183.98 | K79: TRUE | L79: 45921 | M79: 17183.98 | N79: =IF(ABS(VALUE(M79) - VALUE(J79)) > 0.01, TRUE, FALSE) -> FALSE | O79: =IF(OR(K79=FALSE, IFERROR(L79>DATE(2025,12,31), TRUE)), TRUE, FALSE) -> FALSE | P79: =B79 & "|" & (-1 * J79) -> Sunshine Equipment|-17183.98 | Q79: =IF(K79=FALSE, "Unpaid", IF(ISNUMBER(MATCH(P79, Bank_Transactions!H:H, 0)), "Matched in Bank", "Paid but No Bank Match")) -> Paid but No Bank Match
A80: INV2025-0079 | B80: Sunline Electrical | C80: 45907 | D80: 45937 | E80: PRJ-3005 | F80: 6000-Misc-Expense | G80: 12775.48 | H80: Orange | I80: 830.41 | J80: =IF(RAND()<0.23, M80 + RANDBETWEEN(-150,150)/100, M80) -> 13605.89 | K80: TRUE | L80: 45915 | M80: 13605.89 | N80: =IF(ABS(VALUE(M80) - VALUE(J80)) > 0.01, TRUE, FALSE) -> FALSE | O80: =IF(OR(K80=FALSE, IFERROR(L80>DATE(2025,12,31), TRUE)), TRUE, FALSE) -> FALSE | P80: =B80 & "|" & (-1 * J80) -> Sunline Electrical|-13605.89 | Q80: =IF(K80=FALSE, "Unpaid", IF(ISNUMBER(MATCH(P80, Bank_Transactions!H:H, 0)), "Matched in Bank", "Paid but No Bank Match")) -> Paid but No Bank Match
A81: INV2025-0080 | B81: Gulf Coast Telecom | C81: 45673 | D81: 45718 | E81: PRJ-2001 | F81: 5300-Equipment-Rental | G81: 16239.27 | H81: Orange | I81: 1055.55 | J81: =IF(RAND()<0.23, M81 + RANDBETWEEN(-150,150)/100, M81) -> 17294.82 | K81: TRUE | L81: 45709 | M81: 17294.82 | N81: =IF(ABS(VALUE(M81) - VALUE(J81)) > 0.01, TRUE, FALSE) -> FALSE | O81: =IF(OR(K81=FALSE, IFERROR(L81>DATE(2025,12,31), TRUE)), TRUE, FALSE) -> FALSE | P81: =B81 & "|" & (-1 * J81) -> Gulf Coast Telecom|-17294.82 | Q81: =IF(K81=FALSE, "Unpaid", IF(ISNUMBER(MATCH(P81, Bank_Transactions!H:H, 0)), "Matched in Bank", "Paid but No Bank Match")) -> Paid but No Bank Match
A82: INV2025-0081 | B82: Sunline Electrical | C82: 45997 | D82: 46027 | E82: PRJ-2001 | F82: 5100-Materials | G82: 10010.16 | H82: Orange | I82: 650.66 | J82: =IF(RAND()<0.23, M82 + RANDBETWEEN(-150,150)/100, M82) -> 10661.43 | K82: FALSE | M82: 10660.82 | N82: =IF(ABS(VALUE(M82) - VALUE(J82)) > 0.01, TRUE, FALSE) -> TRUE | O82: =IF(OR(K82=FALSE, IFERROR(L82>DATE(2025,12,31), TRUE)), TRUE, FALSE) -> TRUE | P82: =B82 & "|" & (-1 * J82) -> Sunline Electrical|-10661.43 | Q82: =IF(K82=FALSE, "Unpaid", IF(ISNUMBER(MATCH(P82, Bank_Transactions!H:H, 0)), "Matched in Bank", "Paid but No Bank Match")) -> Unpaid
A83: INV2025-0082 | B83: Sunline Electrical | C83: 45836 | D83: 45866 | E83: PRJ-4003 | F83: 5300-Equipment-Rental | G83: 15835.52 | H83: Orange | I83: 1029.31 | J83: =IF(RAND()<0.23, M83 + RANDBETWEEN(-150,150)/100, M83) -> 16864.83 | K83: TRUE | L83: 45880 | M83: 16864.83 | N83: =IF(ABS(VALUE(M83) - VALUE(J83)) > 0.01, TRUE, FALSE) -> FALSE | O83: =IF(OR(K83=FALSE, IFERROR(L83>DATE(2025,12,31), TRUE)), TRUE, FALSE) -> FALSE | P83: =B83 & "|" & (-1 * J83) -> Sunline Electrical|-16864.83 | Q83: =IF(K83=FALSE, "Unpaid", IF(ISNUMBER(MATCH(P83, Bank_Transactions!H:H, 0)), "Matched in Bank", "Paid but No Bank Match")) -> Paid but No Bank Match
A84: INV2025-0083 | B84: BrightPower Partners | C84: 45987 | D84: 46032 | E84: PRJ-3005 | F84: 2100-AP-Trade | G84: 7212.05 | H84: Other_FL | I84: 432.72 | J84: =IF(RAND()<0.23, M84 + RANDBETWEEN(-150,150)/100, M84) -> 7644.77 | K84: FALSE | M84: 7644.77 | N84: =IF(ABS(VALUE(M84) - VALUE(J84)) > 0.01, TRUE, FALSE) -> FALSE | O84: =IF(OR(K84=FALSE, IFERROR(L84>DATE(2025,12,31), TRUE)), TRUE, FALSE) -> TRUE | P84: =B84 & "|" & (-1 * J84) -> BrightPower Partners|-7644.77 | Q84: =IF(K84=FALSE, "Unpaid", IF(ISNUMBER(MATCH(P84, Bank_Transactions!H:H, 0)), "Matched in Bank", "Paid but No Bank Match")) -> Unpaid
A85: INV2025-0084 | B85: Skyline Engineering | C85: 45910 | D85: 45940 | E85: PRJ-2001 | F85: 2100-AP-Trade | G85: 17233.67 | H85: Other_FL | I85: 1034.02 | J85: =IF(RAND()<0.23, M85 + RANDBETWEEN(-150,150)/100, M85) -> 18267.69 | K85: TRUE | L85: 45922 | M85: 18267.69 | N85: =IF(ABS(VALUE(M85) - VALUE(J85)) > 0.01, TRUE, FALSE) -> FALSE | O85: =IF(OR(K85=FALSE, IFERROR(L85>DATE(2025,12,31), TRUE)), TRUE, FALSE) -> FALSE | P85: =B85 & "|" & (-1 * J85) -> Skyline Engineering|-18267.69 | Q85: =IF(K85=FALSE, "Unpaid", IF(ISNUMBER(MATCH(P85, Bank_Transactions!H:H, 0)), "Matched in Bank", "Paid but No Bank Match")) -> Paid but No Bank Match
A86: INV2025-0085 | B86: Sunline Electrical | C86: 45750 | D86: 45780 | E86: PRJ-2001 | F86: 5300-Equipment-Rental | G86: 1070.16 | H86: Hillsborough | I86: 80.26 | J86: =IF(RAND()<0.23, M86 + RANDBETWEEN(-150,150)/100, M86) -> 1150.42 | K86: TRUE | L86: 45761 | M86: 1150.42 | N86: =IF(ABS(VALUE(M86) - VALUE(J86)) > 0.01, TRUE, FALSE) -> FALSE | O86: =IF(OR(K86=FALSE, IFERROR(L86>DATE(2025,12,31), TRUE)), TRUE, FALSE) -> FALSE | P86: =B86 & "|" & (-1 * J86) -> Sunline Electrical|-1150.42 | Q86: =IF(K86=FALSE, "Unpaid", IF(ISNUMBER(MATCH(P86, Bank_Transactions!H:H, 0)), "Matched in Bank", "Paid but No Bank Match")) -> Paid but No Bank Match
A87: INV2025-0086 | B87: Tri-County Services | C87: 45853 | D87: 45898 | E87: PRJ-4003 | F87: 5200-Subcontractors | G87: 9034.25 | H87: Hillsborough | I87: 677.57 | J87: =IF(RAND()<0.23, M87 + RANDBETWEEN(-150,150)/100, M87) -> 9711.82 | K87: FALSE | M87: 9711.82 | N87: =IF(ABS(VALUE(M87) - VALUE(J87)) > 0.01, TRUE, FALSE) -> FALSE | O87: =IF(OR(K87=FALSE, IFERROR(L87>DATE(2025,12,31), TRUE)), TRUE, FALSE) -> TRUE | P87: =B87 & "|" & (-1 * J87) -> Tri-County Services|-9711.82 | Q87: =IF(K87=FALSE, "Unpaid", IF(ISNUMBER(MATCH(P87, Bank_Transactions!H:H, 0)), "Matched in Bank", "Paid but No Bank Match")) -> Unpaid
A88: INV2025-0087 | B88: BrightPower Partners | C88: 45874 | D88: 45919 | E88: PRJ-4003 | F88: 5200-Subcontractors | G88: 7409.85 | H88: Other_FL | I88: 444.59 | J88: =IF(RAND()<0.23, M88 + RANDBETWEEN(-150,150)/100, M88) -> 7853.71 | K88: TRUE | L88: 45902 | M88: 7854.44 | N88: =IF(ABS(VALUE(M88) - VALUE(J88)) > 0.01, TRUE, FALSE) -> TRUE | O88: =IF(OR(K88=FALSE, IFERROR(L88>DATE(2025,12,31), TRUE)), TRUE, FALSE) -> FALSE | P88: =B88 & "|" & (-1 * J88) -> BrightPower Partners|-7853.71 | Q88: =IF(K88=FALSE, "Unpaid", IF(ISNUMBER(MATCH(P88, Bank_Transactions!H:H, 0)), "Matched in Bank", "Paid but No Bank Match")) -> Paid but No Bank Match
A89: INV2025-0088 | B89: Florida Line Crew LLC | C89: 45849 | D89: 45894 | E89: PRJ-2001 | F89: 5100-Materials | G89: 18425.37 | H89: Pinellas | I89: 1289.78 | J89: =IF(RAND()<0.23, M89 + RANDBETWEEN(-150,150)/100, M89) -> 19715.15 | K89: TRUE | L89: 45877 | M89: 19715.15 | N89: =IF(ABS(VALUE(M89) - VALUE(J89)) > 0.01, TRUE, FALSE) -> FALSE | O89: =IF(OR(K89=FALSE, IFERROR(L89>DATE(2025,12,31), TRUE)), TRUE, FALSE) -> FALSE | P89: =B89 & "|" & (-1 * J89) -> Florida Line Crew LLC|-19715.15 | Q89: =IF(K89=FALSE, "Unpaid", IF(ISNUMBER(MATCH(P89, Bank_Transactions!H:H, 0)), "Matched in Bank", "Paid but No Bank Match")) -> Paid but No Bank Match
A90: INV2025-0089 | B90: Bay Area Rentals | C90: 45808 | D90: 45853 | E90: PRJ-1002 | F90: 8900-Other | G90: 21531.11 | H90: Orange | I90: 1399.52 | J90: =IF(RAND()<0.23, M90 + RANDBETWEEN(-150,150)/100, M90) -> 22930.63 | K90: TRUE | L90: 45825 | M90: 22930.63 | N90: =IF(ABS(VALUE(M90) - VALUE(J90)) > 0.01, TRUE, FALSE) -> FALSE | O90: =IF(OR(K90=FALSE, IFERROR(L90>DATE(2025,12,31), TRUE)), TRUE, FALSE) -> FALSE | P90: =B90 & "|" & (-1 * J90) -> Bay Area Rentals|-22930.63 | Q90: =IF(K90=FALSE, "Unpaid", IF(ISNUMBER(MATCH(P90, Bank_Transactions!H:H, 0)), "Matched in Bank", "Paid but No Bank Match")) -> Paid but No Bank Match
A91: INV2025-0090 | B91: Bay Area Rentals | C91: 45936 | D91: 45966 | E91: PRJ-2001 | F91: 5200-Subcontractors | G91: 3026.53 | H91: Pinellas | I91: 211.86 | J91: =IF(RAND()<0.23, M91 + RANDBETWEEN(-150,150)/100, M91) -> 3238.39 | K91: FALSE | M91: 3238.39 | N91: =IF(ABS(VALUE(M91) - VALUE(J91)) > 0.01, TRUE, FALSE) -> FALSE | O91: =IF(OR(K91=FALSE, IFERROR(L91>DATE(2025,12,31), TRUE)), TRUE, FALSE) -> TRUE | P91: =B91 & "|" & (-1 * J91) -> Bay Area Rentals|-3238.39 | Q91: =IF(K91=FALSE, "Unpaid", IF(ISNUMBER(MATCH(P91, Bank_Transactions!H:H, 0)), "Matched in Bank", "Paid but No Bank Match")) -> Unpaid
A92: INV2025-0091 | B92: Bay Area Rentals | C92: 45719 | D92: 45764 | E92: PRJ-3005 | F92: 5300-Equipment-Rental | G92: 10045.64 | H92: Other_FL | I92: 602.74 | J92: =IF(RAND()<0.23, M92 + RANDBETWEEN(-150,150)/100, M92) -> 10648.38 | K92: TRUE | L92: 45742 | M92: 10648.38 | N92: =IF(ABS(VALUE(M92) - VALUE(J92)) > 0.01, TRUE, FALSE) -> FALSE | O92: =IF(OR(K92=FALSE, IFERROR(L92>DATE(2025,12,31), TRUE)), TRUE, FALSE) -> FALSE | P92: =B92 & "|" & (-1 * J92) -> Bay Area Rentals|-10648.38 | Q92: =IF(K92=FALSE, "Unpaid", IF(ISNUMBER(MATCH(P92, Bank_Transactions!H:H, 0)), "Matched in Bank", "Paid but No Bank Match")) -> Paid but No Bank Match
A93: INV2025-0092 | B93: Tri-County Services | C93: 45834 | D93: 45864 | E93: PRJ-4003 | F93: 5300-Equipment-Rental | G93: 23984.27 | H93: Pinellas | I93: 1678.9 | J93: =IF(RAND()<0.23, M93 + RANDBETWEEN(-150,150)/100, M93) -> 25663.17 | K93: TRUE | L93: 45847 | M93: 25663.17 | N93: =IF(ABS(VALUE(M93) - VALUE(J93)) > 0.01, TRUE, FALSE) -> FALSE | O93: =IF(OR(K93=FALSE, IFERROR(L93>DATE(2025,12,31), TRUE)), TRUE, FALSE) -> FALSE | P93: =B93 & "|" & (-1 * J93) -> Tri-County Services|-25663.17 | Q93: =IF(K93=FALSE, "Unpaid", IF(ISNUMBER(MATCH(P93, Bank_Transactions!H:H, 0)), "Matched in Bank", "Paid but No Bank Match")) -> Paid but No Bank Match
A94: INV2025-0093 | B94: Tri-County Services | C94: 45941 | D94: 45971 | E94: PRJ-2001 | F94: 8900-Other | G94: 23789.88 | H94: Orange | I94: 1546.34 | J94: =IF(RAND()<0.23, M94 + RANDBETWEEN(-150,150)/100, M94) -> 25336.22 | K94: TRUE | L94: 45961 | M94: 25336.22 | N94: =IF(ABS(VALUE(M94) - VALUE(J94)) > 0.01, TRUE, FALSE) -> FALSE | O94: =IF(OR(K94=FALSE, IFERROR(L94>DATE(2025,12,31), TRUE)), TRUE, FALSE) -> FALSE | P94: =B94 & "|" & (-1 * J94) -> Tri-County Services|-25336.22 | Q94: =IF(K94=FALSE, "Unpaid", IF(ISNUMBER(MATCH(P94, Bank_Transactions!H:H, 0)), "Matched in Bank", "Paid but No Bank Match")) -> Paid but No Bank Match
A95: INV2025-0094 | B95: Gulf Coast Telecom | C95: 45726 | D95: 45756 | E95: PRJ-2001 | F95: 5100-Materials | G95: 8552.28 | H95: Pinellas | I95: 598.66 | J95: =IF(RAND()<0.23, M95 + RANDBETWEEN(-150,150)/100, M95) -> 9150.94 | K95: TRUE | L95: 45783 | M95: 9150.94 | N95: =IF(ABS(VALUE(M95) - VALUE(J95)) > 0.01, TRUE, FALSE) -> FALSE | O95: =IF(OR(K95=FALSE, IFERROR(L95>DATE(2025,12,31), TRUE)), TRUE, FALSE) -> FALSE | P95: =B95 & "|" & (-1 * J95) -> Gulf Coast Telecom|-9150.94 | Q95: =IF(K95=FALSE, "Unpaid", IF(ISNUMBER(MATCH(P95, Bank_Transactions!H:H, 0)), "Matched in Bank", "Paid but No Bank Match")) -> Paid but No Bank Match
A96: INV2025-0095 | B96: Tampa Grid Services | C96: 45808 | D96: 45838 | E96: PRJ-1001 | F96: 5100-Materials | G96: 3279.88 | H96: Other_FL | I96: 196.79 | J96: =IF(RAND()<0.23, M96 + RANDBETWEEN(-150,150)/100, M96) -> 3476.67 | K96: FALSE | M96: 3476.67 | N96: =IF(ABS(VALUE(M96) - VALUE(J96)) > 0.01, TRUE, FALSE) -> FALSE | O96: =IF(OR(K96=FALSE, IFERROR(L96>DATE(2025,12,31), TRUE)), TRUE, FALSE) -> TRUE | P96: =B96 & "|" & (-1 * J96) -> Tampa Grid Services|-3476.67 | Q96: =IF(K96=FALSE, "Unpaid", IF(ISNUMBER(MATCH(P96, Bank_Transactions!H:H, 0)), "Matched in Bank", "Paid but No Bank Match")) -> Unpaid
A97: INV2025-0096 | B97: Skyline Engineering | C97: 45843 | D97: 45873 | E97: PRJ-3005 | F97: 5300-Equipment-Rental | G97: 13963.46 | H97: Pinellas | I97: 977.44 | J97: =IF(RAND()<0.23, M97 + RANDBETWEEN(-150,150)/100, M97) -> 14940.9 | K97: TRUE | L97: 45865 | M97: 14940.9 | N97: =IF(ABS(VALUE(M97) - VALUE(J97)) > 0.01, TRUE, FALSE) -> FALSE | O97: =IF(OR(K97=FALSE, IFERROR(L97>DATE(2025,12,31), TRUE)), TRUE, FALSE) -> FALSE | P97: =B97 & "|" & (-1 * J97) -> Skyline Engineering|-14940.9 | Q97: =IF(K97=FALSE, "Unpaid", IF(ISNUMBER(MATCH(P97, Bank_Transactions!H:H, 0)), "Matched in Bank", "Paid but No Bank Match")) -> Paid but No Bank Match
A98: INV2025-0097 | B98: BrightPower Partners | C98: 45896 | D98: 45941 | E98: PRJ-3005 | F98: 5300-Equipment-Rental | G98: 19157.01 | H98: Pinellas | I98: 1340.99 | J98: =IF(RAND()<0.23, M98 + RANDBETWEEN(-150,150)/100, M98) -> 20498 | K98: TRUE | L98: 45907 | M98: 20498 | N98: =IF(ABS(VALUE(M98) - VALUE(J98)) > 0.01, TRUE, FALSE) -> FALSE | O98: =IF(OR(K98=FALSE, IFERROR(L98>DATE(2025,12,31), TRUE)), TRUE, FALSE) -> FALSE | P98: =B98 & "|" & (-1 * J98) -> BrightPower Partners|-20498 | Q98: =IF(K98=FALSE, "Unpaid", IF(ISNUMBER(MATCH(P98, Bank_Transactions!H:H, 0)), "Matched in Bank", "Paid but No Bank Match")) -> Paid but No Bank Match
A99: INV2025-0098 | B99: Tampa Grid Services | C99: 45831 | D99: 45861 | E99: PRJ-1001 | F99: 5300-Equipment-Rental | G99: 2282.69 | H99: Pinellas | I99: 159.79 | J99: =IF(RAND()<0.23, M99 + RANDBETWEEN(-150,150)/100, M99) -> 2442.48 | K99: TRUE | L99: 45840 | M99: 2442.48 | N99: =IF(ABS(VALUE(M99) - VALUE(J99)) > 0.01, TRUE, FALSE) -> FALSE | O99: =IF(OR(K99=FALSE, IFERROR(L99>DATE(2025,12,31), TRUE)), TRUE, FALSE) -> FALSE | P99: =B99 & "|" & (-1 * J99) -> Tampa Grid Services|-2442.48 | Q99: =IF(K99=FALSE, "Unpaid", IF(ISNUMBER(MATCH(P99, Bank_Transactions!H:H, 0)), "Matched in Bank", "Paid but No Bank Match")) -> Paid but No Bank Match
A100: INV2025-0099 | B100: Tampa Grid Services | C100: 45686 | D100: 45731 | E100: PRJ-1001 | F100: 5100-Materials | G100: 24672.67 | H100: Hillsborough | I100: 1850.45 | J100: =IF(RAND()<0.23, M100 + RANDBETWEEN(-150,150)/100, M100) -> 26523.12 | K100: TRUE | L100: 45755 | M100: 26523.12 | N100: =IF(ABS(VALUE(M100) - VALUE(J100)) > 0.01, TRUE, FALSE) -> FALSE | O100: =IF(OR(K100=FALSE, IFERROR(L100>DATE(2025,12,31), TRUE)), TRUE, FALSE) -> FALSE | P100: =B100 & "|" & (-1 * J100) -> Tampa Grid Services|-26523.12 | Q100: =IF(K100=FALSE, "Unpaid", IF(ISNUMBER(MATCH(P100, Bank_Transactions!H:H, 0)), "Matched in Bank", "Paid but No Bank Match")) -> Paid but No Bank Match
...

Sheet Bank_Txns
A1: Bank_Txn_ID | B1: Date | C1: Vendor | D1: Description | E1: Amount | F1: Check_ACH | G1: Cleared_Flag | H1: Match_Key | I1: Duplicate_Payment | J1: Duplicate_Payment_Flag
A2: BTXN-00001 | B2: 2025-05-08 | C2: Tri-County Services | D2: Payment for INV2025-0001 | E2: -5343.74 | F2: ACH | G2: True | H2: =C2 & "|" & E2 -> Tri-County Services|-5343.74 | I2: =COUNTIF(H:H, H2) -> 1 | J2: =IF(I2>1, "Duplicate Payment", "OK") -> OK
A3: BTXN-00002 | B3: 2025-05-11 | C3: Atlantic Fiber Co | D3: Payment for INV2025-0002 | E3: -3126.35 | F3: ACH | G3: True | H3: =C3 & "|" & E3 -> Atlantic Fiber Co|-3126.35 | I3: =COUNTIF(H:H, H3) -> 1 | J3: =IF(I3>1, "Duplicate Payment", "OK") -> OK
A4: BTXN-00003 | B4: 2025-06-22 | C4: Sunline Electrical | D4: Payment for INV2025-0003 | E4: -25961.19 | F4: Check | G4: True | H4: =C4 & "|" & E4 -> Sunline Electrical|-25961.19 | I4: =COUNTIF(H:H, H4) -> 1 | J4: =IF(I4>1, "Duplicate Payment", "OK") -> OK
A5: BTXN-00004 | B5: 2025-09-02 | C5: Tidal Contractors | D5: Payment for INV2025-0004 | E5: -16566 | F5: Check | G5: True | H5: =C5 & "|" & E5 -> Tidal Contractors|-16566 | I5: =COUNTIF(H:H, H5) -> 1 | J5: =IF(I5>1, "Duplicate Payment", "OK") -> OK
A6: BTXN-00005 | B6: 2025-11-26 | C6: Tampa Grid Services | D6: Payment for INV2025-0006 | E6: -21118.39 | F6: Check | G6: True | H6: =C6 & "|" & E6 -> Tampa Grid Services|-21118.39 | I6: =COUNTIF(H:H, H6) -> 1 | J6: =IF(I6>1, "Duplicate Payment", "OK") -> OK
A7: BTXN-00006 | B7: 2025-09-26 | C7: Atlantic Fiber Co | D7: Payment for INV2025-0007 | E7: -1736.32 | F7: ACH | G7: True | H7: =C7 & "|" & E7 -> Atlantic Fiber Co|-1736.32 | I7: =COUNTIF(H:H, H7) -> 1 | J7: =IF(I7>1, "Duplicate Payment", "OK") -> OK
A8: BTXN-00007 | B8: 2025-11-02 | C8: BrightPower Partners | D8: Payment for INV2025-0009 | E8: -944.64 | F8: ACH | G8: True | H8: =C8 & "|" & E8 -> BrightPower Partners|-944.64 | I8: =COUNTIF(H:H, H8) -> 1 | J8: =IF(I8>1, "Duplicate Payment", "OK") -> OK
A9: BTXN-00008 | B9: 2025-09-29 | C9: Gulf Coast Telecom | D9: Payment for INV2025-0010 | E9: -24372.83 | F9: ACH | G9: True | H9: =C9 & "|" & E9 -> Gulf Coast Telecom|-24372.83 | I9: =COUNTIF(H:H, H9) -> 1 | J9: =IF(I9>1, "Duplicate Payment", "OK") -> OK
A10: BTXN-00009 | B10: 2025-03-10 | C10: BrightPower Partners | D10: Payment for INV2025-0011 | E10: -5958.22 | F10: ACH | G10: True | H10: =C10 & "|" & E10 -> BrightPower Partners|-5958.22 | I10: =COUNTIF(H:H, H10) -> 1 | J10: =IF(I10>1, "Duplicate Payment", "OK") -> OK
A11: BTXN-00010 | B11: 2025-11-20 | C11: Atlantic Fiber Co | D11: Payment for INV2025-0014 | E11: -20125.99 | F11: ACH | G11: True | H11: =C11 & "|" & E11 -> Atlantic Fiber Co|-20125.99 | I11: =COUNTIF(H:H, H11) -> 1 | J11: =IF(I11>1, "Duplicate Payment", "OK") -> OK
A12: BTXN-00011 | B12: 2025-08-24 | C12: Tampa Grid Services | D12: Payment for INV2025-0015 | E12: -14761.77 | F12: Check | G12: True | H12: =C12 & "|" & E12 -> Tampa Grid Services|-14761.77 | I12: =COUNTIF(H:H, H12) -> 1 | J12: =IF(I12>1, "Duplicate Payment", "OK") -> OK
A13: BTXN-00012 | B13: 2025-11-09 | C13: Tri-County Services | D13: Payment for INV2025-0016 | E13: -28380.53 | F13: Check | G13: True | H13: =C13 & "|" & E13 -> Tri-County Services|-28380.53 | I13: =COUNTIF(H:H, H13) -> 1 | J13: =IF(I13>1, "Duplicate Payment", "OK") -> OK
... A284: BTXN-00283 | B284: 2025-07-15 | C284: BrightPower Partners | D284: Unmatched vendor payment | E284: -644.79 | F284: ACH | G284: True | H284: =C284 & "|" & E284 -> BrightPower Partners|-644.79 | I284: =COUNTIF(H:H, H284) -> 1 | J284: =IF(I284>1, "Duplicate Payment", "OK") -> OK

Sheet GL_AP_Control
A1: Period | B1: AP_Control_Balance | C1: AP_Unpaid_Subledger_Balance
A2: 2025-01 | B2: 350312.46 | C2: 349676.7
A3: 2025-02 | B3: 328655.55 | C3: 337943.22
A4: 2025-03 | B4: 626503.85 | C4: 609374.74
A5: 2025-04 | B5: 672493.32 | C5: 660652.54
A6: 2025-05 | B6: 742770.87 | C6: 752120.23
A7: 2025-06 | B7: 826655.98 | C7: 803516.15
A8: 2025-07 | B8: 765662.09 | C8: 761010.11
A9: 2025-08 | B9: 811937.22 | C9: 807941.66
A10: 2025-09 | B10: 840396.75 | C10: 828071.41
A11: 2025-10 | B11: 992548.61 | C11: 974322.75
A12: 2025-11 | B12: 1061233.14 | C12: 1051362.2
A13: 2025-12 | B13: 1109192.51 | C13: 1134508.22

Sheet Tax_Detail
A1: Invoice_ID | B1: State | C1: Taxable_Amount | D1: Tax_Rate | E1: Calculated_Tax | F1: GL_Tax_Liability_Account | G1: Recalc_Tax | H1: Tax_Mismatch_Flag | I1: Correct_Tax_Rate | J1: Correct_Rate_Flag
A2: INV2025-0001 | B2: FL | C2: 4994.15 | D2: 0.07 | E2: =IF(RAND() < 0.12, CHOOSE(RANDBETWEEN(1,4), 0, ROUND(C2 * (D2 - 0.01), 2), ROUND(C2 * (D2 + 0.01), 2), ROUND(C2 * D2 * 2, 2) ), ROUND(C2 * D2, 2) ) -> 349.59 | F2: 2020-SalesUseTaxPayable | G2: =ROUND(C2 * D2, 2) -> 349.59 | H2: =IF(ABS(E2 - G2) > 0.01, "Mismatch", "OK") -> OK | I2: {=IFERROR(XLOOKUP(XLOOKUP(A2, AP_Subledger!A:A, AP_Subledger!H:H), Tax_Rates_Reference!A:A, Tax_Rates_Reference!C:C), "")} -> 0.07 | J2: =IF(I2="", "", IF(ABS(D2 - I2) < 0.0001, TRUE, FALSE)) -> TRUE
A3: INV2025-0002 | B3: FL | C3: 2949.39 | D3: 0.06 | E3: =IF(RAND() < 0.12, CHOOSE(RANDBETWEEN(1,4), 0, ROUND(C3 * (D3 - 0.01), 2), ROUND(C3 * (D3 + 0.01), 2), ROUND(C3 * D3 * 2, 2) ), ROUND(C3 * D3, 2) ) -> 176.96 | F3: 2020-SalesUseTaxPayable | G3: =ROUND(C3 * D3, 2) -> 176.96 | H3: =IF(ABS(E3 - G3) > 0.01, "Mismatch", "OK") -> OK | I3: {=IFERROR(XLOOKUP(XLOOKUP(A3, AP_Subledger!A:A, AP_Subledger!H:H), Tax_Rates_Reference!A:A, Tax_Rates_Reference!C:C), "")} -> 0.06 | J3: =IF(I3="", "", IF(ABS(D3 - I3) < 0.0001, TRUE, FALSE)) -> TRUE
A4: INV2025-0003 | B4: FL | C4: 24262.79 | D4: 0.07 | E4: =IF(RAND() < 0.12, CHOOSE(RANDBETWEEN(1,4), 0, ROUND(C4 * (D4 - 0.01), 2), ROUND(C4 * (D4 + 0.01), 2), ROUND(C4 * D4 * 2, 2) ), ROUND(C4 * D4, 2) ) -> 1698.4 | F4: 2020-SalesUseTaxPayable | G4: =ROUND(C4 * D4, 2) -> 1698.4 | H4: =IF(ABS(E4 - G4) > 0.01, "Mismatch", "OK") -> OK | I4: {=IFERROR(XLOOKUP(XLOOKUP(A4, AP_Subledger!A:A, AP_Subledger!H:H), Tax_Rates_Reference!A:A, Tax_Rates_Reference!C:C), "")} -> 0.07 | J4: =IF(I4="", "", IF(ABS(D4 - I4) < 0.0001, TRUE, FALSE)) -> TRUE
A5: INV2025-0004 | B5: FL | C5: 15628.3 | D5: 0.06 | E5: =IF(RAND() < 0.12, CHOOSE(RANDBETWEEN(1,4), 0, ROUND(C5 * (D5 - 0.01), 2), ROUND(C5 * (D5 + 0.01), 2), ROUND(C5 * D5 * 2, 2) ), ROUND(C5 * D5, 2) ) -> 937.7 | F5: 2020-SalesUseTaxPayable | G5: =ROUND(C5 * D5, 2) -> 937.7 | H5: =IF(ABS(E5 - G5) > 0.01, "Mismatch", "OK") -> OK | I5: {=IFERROR(XLOOKUP(XLOOKUP(A5, AP_Subledger!A:A, AP_Subledger!H:H), Tax_Rates_Reference!A:A, Tax_Rates_Reference!C:C), "")} -> 0.06 | J5: =IF(I5="", "", IF(ABS(D5 - I5) < 0.0001, TRUE, FALSE)) -> TRUE
A6: INV2025-0005 | B6: FL | C6: 1643.31 | D6: 0.075 | E6: =IF(RAND() < 0.12, CHOOSE(RANDBETWEEN(1,4), 0, ROUND(C6 * (D6 - 0.01), 2), ROUND(C6 * (D6 + 0.01), 2), ROUND(C6 * D6 * 2, 2) ), ROUND(C6 * D6, 2) ) -> 123.25 | F6: 2020-SalesUseTaxPayable | G6: =ROUND(C6 * D6, 2) -> 123.25 | H6: =IF(ABS(E6 - G6) > 0.01, "Mismatch", "OK") -> OK | I6: {=IFERROR(XLOOKUP(XLOOKUP(A6, AP_Subledger!A:A, AP_Subledger!H:H), Tax_Rates_Reference!A:A, Tax_Rates_Reference!C:C), "")} -> 0.075 | J6: =IF(I6="", "", IF(ABS(D6 - I6) < 0.0001, TRUE, FALSE)) -> TRUE
A7: INV2025-0006 | B7: FL | C7: 19736.81 | D7: 0.07 | E7: =IF(RAND() < 0.12, CHOOSE(RANDBETWEEN(1,4), 0, ROUND(C7 * (D7 - 0.01), 2), ROUND(C7 * (D7 + 0.01), 2), ROUND(C7 * D7 * 2, 2) ), ROUND(C7 * D7, 2) ) -> 1381.58 | F7: 2020-SalesUseTaxPayable | G7: =ROUND(C7 * D7, 2) -> 1381.58 | H7: =IF(ABS(E7 - G7) > 0.01, "Mismatch", "OK") -> OK | I7: {=IFERROR(XLOOKUP(XLOOKUP(A7, AP_Subledger!A:A, AP_Subledger!H:H), Tax_Rates_Reference!A:A, Tax_Rates_Reference!C:C), "")} -> 0.07 | J7: =IF(I7="", "", IF(ABS(D7 - I7) < 0.0001, TRUE, FALSE)) -> TRUE
A8: INV2025-0007 | B8: FL | C8: 1638.04 | D8: 0.08 | E8: =IF(RAND() < 0.12, CHOOSE(RANDBETWEEN(1,4), 0, ROUND(C8 * (D8 - 0.01), 2), ROUND(C8 * (D8 + 0.01), 2), ROUND(C8 * D8 * 2, 2) ), ROUND(C8 * D8, 2) ) -> 131.04 | F8: 2020-SalesUseTaxPayable | G8: =ROUND(C8 * D8, 2) -> 131.04 | H8: =IF(ABS(E8 - G8) > 0.01, "Mismatch", "OK") -> OK | I8: {=IFERROR(XLOOKUP(XLOOKUP(A8, AP_Subledger!A:A, AP_Subledger!H:H), Tax_Rates_Reference!A:A, Tax_Rates_Reference!C:C), "")} -> 0.06 | J8: =IF(I8="", "", IF(ABS(D8 - I8) < 0.0001, TRUE, FALSE)) -> FALSE
A9: INV2025-0008 | B9: FL | C9: 23747.7 | D9: 0.075 | E9: =IF(RAND() < 0.12, CHOOSE(RANDBETWEEN(1,4), 0, ROUND(C9 * (D9 - 0.01), 2), ROUND(C9 * (D9 + 0.01), 2), ROUND(C9 * D9 * 2, 2) ), ROUND(C9 * D9, 2) ) -> 1781.08 | F9: 2020-SalesUseTaxPayable | G9: =ROUND(C9 * D9, 2) -> 1781.08 | H9: =IF(ABS(E9 - G9) > 0.01, "Mismatch", "OK") -> OK | I9: {=IFERROR(XLOOKUP(XLOOKUP(A9, AP_Subledger!A:A, AP_Subledger!H:H), Tax_Rates_Reference!A:A, Tax_Rates_Reference!C:C), "")} -> 0.075 | J9: =IF(I9="", "", IF(ABS(D9 - I9) < 0.0001, TRUE, FALSE)) -> TRUE
A10: INV2025-0009 | B10: FL | C10: 891.17 | D10: 0.04 | E10: =IF(RAND() < 0.12, CHOOSE(RANDBETWEEN(1,4), 0, ROUND(C10 * (D10 - 0.01), 2), ROUND(C10 * (D10 + 0.01), 2), ROUND(C10 * D10 * 2, 2) ), ROUND(C10 * D10, 2) ) -> 35.65 | F10: 2020-SalesUseTaxPayable | G10: =ROUND(C10 * D10, 2) -> 35.65 | H10: =IF(ABS(E10 - G10) > 0.01, "Mismatch", "OK") -> OK | I10: {=IFERROR(XLOOKUP(XLOOKUP(A10, AP_Subledger!A:A, AP_Subledger!H:H), Tax_Rates_Reference!A:A, Tax_Rates_Reference!C:C), "")} -> 0.06 | J10: =IF(I10="", "", IF(ABS(D10 - I10) < 0.0001, TRUE, FALSE)) -> FALSE
A11: INV2025-0010 | B11: FL | C11: 22778.35 | D11: 0.07 | E11: =IF(RAND() < 0.12, CHOOSE(RANDBETWEEN(1,4), 0, ROUND(C11 * (D11 - 0.01), 2), ROUND(C11 * (D11 + 0.01), 2), ROUND(C11 * D11 * 2, 2) ), ROUND(C11 * D11, 2) ) -> 1594.48 | F11: 2020-SalesUseTaxPayable | G11: =ROUND(C11 * D11, 2) -> 1594.48 | H11: =IF(ABS(E11 - G11) > 0.01, "Mismatch", "OK") -> OK | I11: {=IFERROR(XLOOKUP(XLOOKUP(A11, AP_Subledger!A:A, AP_Subledger!H:H), Tax_Rates_Reference!A:A, Tax_Rates_Reference!C:C), "")} -> 0.07 | J11: =IF(I11="", "", IF(ABS(D11 - I11) < 0.0001, TRUE, FALSE)) -> TRUE
A12: INV2025-0011 | B12: FL | C12: 5594.57 | D12: 0.065 | E12: =IF(RAND() < 0.12, CHOOSE(RANDBETWEEN(1,4), 0, ROUND(C12 * (D12 - 0.01), 2), ROUND(C12 * (D12 + 0.01), 2), ROUND(C12 * D12 * 2, 2) ), ROUND(C12 * D12, 2) ) -> 363.65 | F12: 2020-SalesUseTaxPayable | G12: =ROUND(C12 * D12, 2) -> 363.65 | H12: =IF(ABS(E12 - G12) > 0.01, "Mismatch", "OK") -> OK | I12: {=IFERROR(XLOOKUP(XLOOKUP(A12, AP_Subledger!A:A, AP_Subledger!H:H), Tax_Rates_Reference!A:A, Tax_Rates_Reference!C:C), "")} -> 0.065 | J12: =IF(I12="", "", IF(ABS(D12 - I12) < 0.0001, TRUE, FALSE)) -> TRUE
A13: INV2025-0012 | B13: FL | C13: 10181.18 | D13: 0.065 | E13: =IF(RAND() < 0.12, CHOOSE(RANDBETWEEN(1,4), 0, ROUND(C13 * (D13 - 0.01), 2), ROUND(C13 * (D13 + 0.01), 2), ROUND(C13 * D13 * 2, 2) ), ROUND(C13 * D13, 2) ) -> 661.78 | F13: 2020-SalesUseTaxPayable | G13: =ROUND(C13 * D13, 2) -> 661.78 | H13: =IF(ABS(E13 - G13) > 0.01, "Mismatch", "OK") -> OK | I13: {=IFERROR(XLOOKUP(XLOOKUP(A13, AP_Subledger!A:A, AP_Subledger!H:H), Tax_Rates_Reference!A:A, Tax_Rates_Reference!C:C), "")} -> 0.065 | J13: =IF(I13="", "", IF(ABS(D13 - I13) < 0.0001, TRUE, FALSE)) -> TRUE
... A351: INV2025-0350 | B351: FL | C351: 10886.65 | D351: 0.065 | E351: =IF(RAND() < 0.12, CHOOSE(RANDBETWEEN(1,4), 0, ROUND(C351 * (D351 - 0.01), 2), ROUND(C351 * (D351 + 0.01), 2), ROUND(C351 * D351 * 2, 2) ), ROUND(C351 * D351, 2) ) -> 707.63 | F351: 2020-SalesUseTaxPayable | G351: =ROUND(C351 * D351, 2) -> 707.63 | H351: =IF(ABS(E351 - G351) > 0.01, "Mismatch", "OK") -> OK | I351: {=IFERROR(XLOOKUP(XLOOKUP(A351, AP_Subledger!A:A, AP_Subledger!H:H), Tax_Rates_Reference!A:A, Tax_Rates_Reference!C:C), "")} -> 0.065 | J351: =IF(I351="", "", IF(ABS(D351 - I351) < 0.0001, TRUE, FALSE)) -> TRUE

Sheet Tax_Rates_Reference
A1: Tax_Jurisdiction | B1: Surtax_2025 | C1: Total_Tax_Rate_2025
A2: Hillsborough | B2: 0.015 | C2: 0.075
A3: Pinellas | B3: 0.01 | C3: 0.07
A4: Orange | B4: 0.005 | C4: 0.065
A5: Other_FL | B5: 0 | C5: 0.06

Sheet GL_Trial_Balance_Summary
A1: Account | B1: Ending_Balance
A2: 2000-AccountsPayable | B2: =SUM(AP_Subledger!J:J) * -1 -> -5034825.8
A3: 1000-Cash | B3: 350000
A4: 2020-SalesUseTaxPayable | B4: 14850
A5: 2500-LeaseLiability | B5: 420000
A6: 1800-ROUAsset | B6: 395000
A7: 6000-LeaseExpense | B7: 225000
A8: 6100-DepreciationROU | B8: 195000

Sheet Lease_Pivot

Sheet Lease_Schedule
A1: Lease_ID | B1: Start_Date | C1: Payment_Date | D1: Lease_Payment | E1: Interest_Portion | F1: Principal_Portion | G1: Ending_Lease_Liability | H1: ROU_Asset_Balance | I1: IP_Sum | J1: IP_Sum_Diff | K1: IP_Sum_Mismatch_Flag | L1: Sequence_Check
A2: LSE-001 | B2: 45658 | C2: 45658 | D2: 5684.7 | E2: 1037.27 | F2: 4647.43 | G2: 179699.41 | H2: 179699.41 | I2: 5684.700000000001 | J2: -9.094947017729282e-13 | K2: False | L2: =IF(ROW()=2, "OK", IF(C2 = EDATE(C1, 1), "OK", "Sequence Error")) -> OK
A3: LSE-001 | B3: 45658 | C3: 45689 | D3: 5684.7 | E3: 1011.19 | F3: 4673.51 | G3: 174565.14 | H3: 174565.14 | I3: 5684.700000000001 | J3: -9.094947017729282e-13 | K3: False | L3: =IF(ROW()=2, "OK", IF(C3 = EDATE(C2, 1), "OK", "Sequence Error")) -> OK
A4: LSE-001 | B4: 45658 | C4: 45717 | D4: 5684.7 | E4: 984.96 | F4: 4699.74 | G4: 169430.87 | H4: 169430.87 | I4: 5684.7 | J4: 0.0 | K4: False | L4: =IF(ROW()=2, "OK", IF(C4 = EDATE(C3, 1), "OK", "Sequence Error")) -> OK
A5: LSE-001 | B5: 45658 | C5: 45778 | D5: 5684.7 | E5: 932.07 | F5: 4752.63 | G5: 159162.33 | H5: 159162.33 | I5: 5684.7 | J5: 0.0 | K5: False | L5: =IF(ROW()=2, "OK", IF(C5 = EDATE(C4, 1), "OK", "Sequence Error")) -> Sequence Error
A6: LSE-001 | B6: 45658 | C6: 45809 | D6: 5684.7 | E6: 905.39 | F6: 4779.31 | G6: 154028.06 | H6: 154028.06 | I6: 5684.700000000001 | J6: -9.094947017729282e-13 | K6: False | L6: =IF(ROW()=2, "OK", IF(C6 = EDATE(C5, 1), "OK", "Sequence Error")) -> OK
A7: LSE-001 | B7: 45658 | C7: 45839 | D7: 5684.7 | E7: 878.57 | F7: 4806.13 | G7: 148893.79 | H7: 148893.79 | I7: 5684.7 | J7: 0.0 | K7: False | L7: =IF(ROW()=2, "OK", IF(C7 = EDATE(C6, 1), "OK", "Sequence Error")) -> OK
A8: LSE-001 | B8: 45658 | C8: 45870 | D8: 5684.7 | E8: 851.6 | F8: 4833.1 | G8: 143759.52 | H8: 143759.52 | I8: 5684.700000000001 | J8: -9.094947017729282e-13 | K8: False | L8: =IF(ROW()=2, "OK", IF(C8 = EDATE(C7, 1), "OK", "Sequence Error")) -> OK
A9: LSE-001 | B9: 45658 | C9: 45901 | D9: 5684.7 | E9: 824.48 | F9: 4860.22 | G9: 138625.25 | H9: 138625.25 | I9: 5684.700000000001 | J9: -9.094947017729282e-13 | K9: False | L9: =IF(ROW()=2, "OK", IF(C9 = EDATE(C8, 1), "OK", "Sequence Error")) -> OK
A10: LSE-001 | B10: 45658 | C10: 45931 | D10: 5684.7 | E10: 797.2 | F10: 4887.5 | G10: 133490.98 | H10: 133490.98 | I10: 5684.7 | J10: 0.0 | K10: False | L10: =IF(ROW()=2, "OK", IF(C10 = EDATE(C9, 1), "OK", "Sequence Error")) -> OK
A11: LSE-001 | B11: 45658 | C11: 45962 | D11: 5684.7 | E11: 769.78 | F11: 4914.92 | G11: 128356.71 | H11: 128356.71 | I11: 5684.7 | J11: 0.0 | K11: False | L11: =IF(ROW()=2, "OK", IF(C11 = EDATE(C10, 1), "OK", "Sequence Error")) -> OK
A12: LSE-001 | B12: 45658 | C12: 45992 | D12: 5684.7 | E12: 742.19 | F12: 4942.51 | G12: 123222.44 | H12: 123222.44 | I12: 5684.700000000001 | J12: -9.094947017729282e-13 | K12: False | L12: =IF(ROW()=2, "OK", IF(C12 = EDATE(C11, 1), "OK", "Sequence Error")) -> OK
A13: LSE-001 | B13: 45658 | C13: 46023 | D13: 5684.7 | E13: 714.46 | F13: 4970.24 | G13: 118088.17 | H13: 118088.17 | I13: 5684.7 | J13: 0.0 | K13: False | L13: =IF(ROW()=2, "OK", IF(C13 = EDATE(C12, 1), "OK", "Sequence Error")) -> OK
... A121: LSE-004 | B121: 45809 | C121: 46508 | D121: 4147.33 | E121: 29.13 | F121: 4118.2 | G121: 0 | H121: 0 | I121: 4147.33 | J121: 0.0 | K121: False | L121: =IF(ROW()=2, "OK", IF(C121 = EDATE(C120, 1), "OK", "Sequence Error")) -> OK

Sheet Reconciliation_Summary
A1: AP_Unpaid_Total | B1: GL_AP_Control_Balance_Cell | C1: Variance (GL − Subledger) | D1: GL_Missing_Items | E1: Paid_per_AP | F1: Payments_per_Bank | G1: Variance_bank | H1: Paid_no_bank_match | I1: duplicate_payments | J1: Invoice_Tax_Total | K1: GL_Tax_Payable | L1: Variance_GL_Invoice_Tax | M1: Lease_Liability_Total | N1: ROU_Asset_Total | O1: GL_Lease_Liability | P1: GL_ROU_Asset | Q1: GL_Lease_Liability_Variance | R1: GL_ROU_Asset_Variance | S1: Sequence_Error
A2: =SUMIFS(AP_Subledger!J:J, AP_Subledger!O:O, TRUE) -> 1134501.7 | B2: {=INDEX(GL_AP_Control!B:B, MATCH("2025-12", GL_AP_Control!A:A, 0))} -> 1109192.51 | C2: =B2-A2 -> -25309.16 | D2: =IF(COUNTIF(AP_Subledger!P:P, "Missing")>0, "Missing Items", "OK") -> OK | E2: =SUMIFS(AP_Subledger!J:J, AP_Subledger!K:K, TRUE) -> 3900324.1 | F2: =SUM(Bank_Txns!E:E) * -1 -> 4058113.5 | G2: =F2-E2 -> 157789.39 | H2: =COUNTIF(AP_Subledger!Q:Q, "Paid but No Bank Match") -> 265 | I2: =COUNTIF(Bank_Txns!J:J, "Duplicate Payment") -> 16 | J2: =SUM(Tax_Detail!E:E) -> 329408.99 | K2: {=XLOOKUP("2020-SalesUseTaxPayable", GL_Trial_Balance_Summary!A:A, GL_Trial_Balance_Summary!B:B)} -> 14850 | L2: =K2-J2 -> -314558.99 | M2: =SUM(Lease_Pivot!C5:C8) -> 462441.95 | N2: =SUM(Lease_Pivot!D5:D8) -> 462441.95 | O2: {=XLOOKUP("2500-LeaseLiability", GL_Trial_Balance_Summary!A:A, GL_Trial_Balance_Summary!B:B)} -> 420000 | P2: {=XLOOKUP("1800-ROUAsset", GL_Trial_Balance_Summary!A:A, GL_Trial_Balance_Summary!B:B)} -> 395000 | Q2: =O2-M2 -> -42441.95 | R2: =P2-N2 -> -67441.95 | S2: =COUNTIF(Lease_Schedule!L:L, "Sequence Error") -> 6
